{
  "data": [
    {
      "id": 21215488,
      "name": "gome Ⓜ️Ⓜ️T (❖,❖)",
      "rank": 1,
      "user_id": "-1",
      "topic_id": "INTEGRA",
      "username": "hangome_sol",
      "mindshare": 6.33,
      "projectId": 248,
      "duration": "7D",
      "updatedAt": 1760702633694,
      "follower_count": 4107,
      "smart_follower_count": 161,
      "insightfullness": null,
      "originality": null,
      "yaps_all": 177.43
    },
    {
      "id": 21215489,
      "name": "Nick Research",
      "rank": 2,
      "user_id": "-1",
      "topic_id": "INTEGRA",
      "username": "Nick_Researcher",
      "mindshare": 4.94,
      "projectId": 248,
      "duration": "7D",
      "updatedAt": 1760702633694,
      "follower_count": 10644,
      "smart_follower_count": 136,
      "insightfullness": null,
      "originality": null,
      "yaps_all": 664.61
    },
    {
      "id": 21215490,
      "name": "Defi Rocketeer",
      "rank": 3,
      "user_id": "-1",
      "topic_id": "INTEGRA",
      "username": "Defi_Rocketeer",
      "mindshare": 3.65,
      "projectId": 248,
      "duration": "7D",
      "updatedAt": 1760702633694,
      "follower_count": 170928,
      "smart_follower_count": 177,
      "insightfullness": null,
      "originality": null,
      "yaps_all": 297.61
    },
    {
      "id": 21215491,
      "name": "Gyo",
      "rank": 4,
      "user_id": "-1",
      "topic_id": "INTEGRA",
      "username": "Gyokeres_eth",
      "mindshare": 2.92,
      "projectId": 248,
      "duration": "7D",
      "updatedAt": 1760702633694,
      "follower_count": 12345,
      "smart_follower_count": 135,
      "insightfullness": null,
      "originality": null,
      "yaps_all": 244.63
    },
    {
      "id": 21215492,
      "name": "omni.crypto 🥵",
      "rank": 5,
      "user_id": "-1",
      "topic_id": "INTEGRA",
      "username": "omnicryptx",
      "mindshare": 2.68,
      "projectId": 248,
      "duration": "7D",
      "updatedAt": 1760702633694,
      "follower_count": 7740,
      "smart_follower_count": 113,
      "insightfullness": null,
      "originality": null,
      "yaps_all": 365.11
    },
    {
      "id": 21215493,
      "name": "Lilo",
      "rank": 6,
      "user_id": "-1",
      "topic_id": "INTEGRA",
      "username": "lilo_nft",
      "mindshare": 2.64,
      "projectId": 248,
      "duration": "7D",
      "updatedAt": 1760702633694,
      "follower_count": 6519,
      "smart_follower_count": 94,
      "insightfullness": null,
      "originality": null,
      "yaps_all": null
    },
    {
      "id": 21215494,
      "name": "Daniva",
      "rank": 7,
      "user_id": "-1",
      "topic_id": "INTEGRA",
      "username": "danivaweb3",
      "mindshare": 2.13,
      "projectId": 248,
      "duration": "7D",
      "updatedAt": 1760702633694,
      "follower_count": 8118,
      "smart_follower_count": 24,
      "insightfullness": null,
      "originality": null,
      "yaps_all": 128.87
    },
    {
      "id": 21215495,
      "name": "쥔장 Ⓜ️Ⓜ️T",
      "rank": 8,
      "user_id": "-1",
      "topic_id": "INTEGRA",
      "username": "beingRich2000",
      "mindshare": 1.98,
      "projectId": 248,
      "duration": "7D",
      "updatedAt": 1760702633694,
      "follower_count": 12512,
      "smart_follower_count": 198,
      "insightfullness": null,
      "originality": null,
      "yaps_all": 839.98
    },
    {
      "id": 21215496,
      "name": "Kaff 📊",
      "rank": 9,
      "user_id": "-1",
      "topic_id": "INTEGRA",
      "username": "Kaffchad",
      "mindshare": 1.89,
      "projectId": 248,
      "duration": "7D",
      "updatedAt": 1760702633694,
      "follower_count": 20600,
      "smart_follower_count": 197,
      "insightfullness": null,
      "originality": null,
      "yaps_all": null
    },
    {
      "id": 21215497,
      "name": "FAB__AMY (✧ᴗ✧)",
      "rank": 10,
      "user_id": "-1",
      "topic_id": "INTEGRA",
      "username": "Iam__Attracta",
      "mindshare": 1.83,
      "projectId": 248,
      "duration": "7D",
      "updatedAt": 1760702633694,
      "follower_count": 1900,
      "smart_follower_count": 18,
      "insightfullness": null,
      "originality": null,
      "yaps_all": 51.65
    },
    {
      "id": 21215498,
      "name": "Usopp",
      "rank": 11,
      "user_id": "-1",
      "topic_id": "INTEGRA",
      "username": "CryptoUsopp",
      "mindshare": 1.77,
      "projectId": 248,
      "duration": "7D",
      "updatedAt": 1760702633694,
      "follower_count": 41434,
      "smart_follower_count": 311,
      "insightfullness": null,
      "originality": null,
      "yaps_all": 973.25
    },
    {
      "id": 21215499,
      "name": "코생 (파머) Ⓜ️Ⓜ️T",
      "rank": 12,
      "user_id": "-1",
      "topic_id": "INTEGRA",
      "username": "auz2or",
      "mindshare": 1.69,
      "projectId": 248,
      "duration": "7D",
      "updatedAt": 1760702633694,
      "follower_count": 4479,
      "smart_follower_count": 120,
      "insightfullness": null,
      "originality": null,
      "yaps_all": 324.4
    },
    {
      "id": 21215500,
      "name": "HEINRICH",
      "rank": 13,
      "user_id": "-1",
      "topic_id": "INTEGRA",
      "username": "HeinrichDefi",
      "mindshare": 1.64,
      "projectId": 248,
      "duration": "7D",
      "updatedAt": 1760702633694,
      "follower_count": 22344,
      "smart_follower_count": 68,
      "insightfullness": null,
      "originality": null,
      "yaps_all": 157.98
    },
    {
      "id": 21215501,
      "name": "VETRA ⚙️",
      "rank": 14,
      "user_id": "-1",
      "topic_id": "INTEGRA",
      "username": "0X_Vetra",
      "mindshare": 1.63,
      "projectId": 248,
      "duration": "7D",
      "updatedAt": 1760702633694,
      "follower_count": 7606,
      "smart_follower_count": 14,
      "insightfullness": null,
      "originality": null,
      "yaps_all": 111.09
    },
    {
      "id": 21215502,
      "name": "Derpy",
      "rank": 15,
      "user_id": "-1",
      "topic_id": "INTEGRA",
      "username": "ice8018",
      "mindshare": 1.62,
      "projectId": 248,
      "duration": "7D",
      "updatedAt": 1760702633694,
      "follower_count": 663,
      "smart_follower_count": 20,
      "insightfullness": null,
      "originality": null,
      "yaps_all": null
    },
    {
      "id": 21215503,
      "name": "냐옹쩌둥Ⓜ️Ⓜ️T",
      "rank": 16,
      "user_id": "-1",
      "topic_id": "INTEGRA",
      "username": "whenmoonsoon",
      "mindshare": 1.6,
      "projectId": 248,
      "duration": "7D",
      "updatedAt": 1760702633694,
      "follower_count": 4035,
      "smart_follower_count": 115,
      "insightfullness": null,
      "originality": null,
      "yaps_all": 79.66
    },
    {
      "id": 21215504,
      "name": "Maya 💙💛",
      "rank": 17,
      "user_id": "-1",
      "topic_id": "INTEGRA",
      "username": "Mayacrypt",
      "mindshare": 1.51,
      "projectId": 248,
      "duration": "7D",
      "updatedAt": 1760702633694,
      "follower_count": 25262,
      "smart_follower_count": 13,
      "insightfullness": null,
      "originality": null,
      "yaps_all": null
    },
    {
      "id": 21215505,
      "name": "파워업 수비 SUBI🥕 Ⓜ️Ⓜ️T",
      "rank": 18,
      "user_id": "-1",
      "topic_id": "INTEGRA",
      "username": "cryptomakase",
      "mindshare": 1.35,
      "projectId": 248,
      "duration": "7D",
      "updatedAt": 1760702633694,
      "follower_count": 2228,
      "smart_follower_count": 50,
      "insightfullness": null,
      "originality": null,
      "yaps_all": null
    },
    {
      "id": 21215506,
      "name": "胖虎Ⓜ️Ⓜ️T",
      "rank": 19,
      "user_id": "-1",
      "topic_id": "INTEGRA",
      "username": "NFT99807",
      "mindshare": 1.33,
      "projectId": 248,
      "duration": "7D",
      "updatedAt": 1760702633694,
      "follower_count": 2421,
      "smart_follower_count": 21,
      "insightfullness": null,
      "originality": null,
      "yaps_all": null
    },
    {
      "id": 21215507,
      "name": "헤다 heda Ⓜ️Ⓜ️T",
      "rank": 20,
      "user_id": "-1",
      "topic_id": "INTEGRA",
      "username": "hedacool",
      "mindshare": 1.26,
      "projectId": 248,
      "duration": "7D",
      "updatedAt": 1760702633694,
      "follower_count": 6807,
      "smart_follower_count": 154,
      "insightfullness": null,
      "originality": null,
      "yaps_all": 553.81
    },
    {
      "id": 21215508,
      "name": "레오.Master Ⓜ️Ⓜ️T",
      "rank": 21,
      "user_id": "-1",
      "topic_id": "INTEGRA",
      "username": "ezeroho8245",
      "mindshare": 1.25,
      "projectId": 248,
      "duration": "7D",
      "updatedAt": 1760702633694,
      "follower_count": 11118,
      "smart_follower_count": 122,
      "insightfullness": null,
      "originality": null,
      "yaps_all": 598.26
    },
    {
      "id": 21215509,
      "name": "Gushydon",
      "rank": 22,
      "user_id": "-1",
      "topic_id": "INTEGRA",
      "username": "Gushydon10",
      "mindshare": 1.22,
      "projectId": 248,
      "duration": "7D",
      "updatedAt": 1760702633694,
      "follower_count": 2107,
      "smart_follower_count": 21,
      "insightfullness": null,
      "originality": null,
      "yaps_all": null
    },
    {
      "id": 21215510,
      "name": "Dejun | 德君 - Ⓜ️Ⓜ️T",
      "rank": 23,
      "user_id": "-1",
      "topic_id": "INTEGRA",
      "username": "0xDejun",
      "mindshare": 1.15,
      "projectId": 248,
      "duration": "7D",
      "updatedAt": 1760702633694,
      "follower_count": 1647,
      "smart_follower_count": 22,
      "insightfullness": null,
      "originality": null,
      "yaps_all": 45.86
    },
    {
      "id": 21215511,
      "name": "0xsassy",
      "rank": 24,
      "user_id": "-1",
      "topic_id": "INTEGRA",
      "username": "0xsassyyy",
      "mindshare": 1.09,
      "projectId": 248,
      "duration": "7D",
      "updatedAt": 1760702633694,
      "follower_count": 1800,
      "smart_follower_count": 19,
      "insightfullness": null,
      "originality": null,
      "yaps_all": 56.02
    },
    {
      "id": 21215512,
      "name": "Gurabang🍚 ⛓",
      "rank": 25,
      "user_id": "-1",
      "topic_id": "INTEGRA",
      "username": "imgihwan14",
      "mindshare": 1.07,
      "projectId": 248,
      "duration": "7D",
      "updatedAt": 1760702633694,
      "follower_count": 583,
      "smart_follower_count": 9,
      "insightfullness": null,
      "originality": null,
      "yaps_all": null
    },
    {
      "id": 21215513,
      "name": "Paws🐾",
      "rank": 26,
      "user_id": "-1",
      "topic_id": "INTEGRA",
      "username": "kvzzan",
      "mindshare": 0.92,
      "projectId": 248,
      "duration": "7D",
      "updatedAt": 1760702633694,
      "follower_count": 1311,
      "smart_follower_count": 7,
      "insightfullness": null,
      "originality": null,
      "yaps_all": null
    },
    {
      "id": 21215514,
      "name": "Bitcoin Özgür",
      "rank": 27,
      "user_id": "-1",
      "topic_id": "INTEGRA",
      "username": "Btcozgurr",
      "mindshare": 0.9,
      "projectId": 248,
      "duration": "7D",
      "updatedAt": 1760702633694,
      "follower_count": 3245,
      "smart_follower_count": 18,
      "insightfullness": null,
      "originality": null,
      "yaps_all": 25.36
    },
    {
      "id": 21215515,
      "name": "Josh in web 3",
      "rank": 28,
      "user_id": "-1",
      "topic_id": "INTEGRA",
      "username": "JoshJosh45",
      "mindshare": 0.88,
      "projectId": 248,
      "duration": "7D",
      "updatedAt": 1760702633694,
      "follower_count": 3259,
      "smart_follower_count": 16,
      "insightfullness": null,
      "originality": null,
      "yaps_all": 10.19
    },
    {
      "id": 21215516,
      "name": "CrYpT_DoN💎",
      "rank": 29,
      "user_id": "-1",
      "topic_id": "INTEGRA",
      "username": "0x_DoNjayy",
      "mindshare": 0.83,
      "projectId": 248,
      "duration": "7D",
      "updatedAt": 1760702633694,
      "follower_count": 2487,
      "smart_follower_count": 14,
      "insightfullness": null,
      "originality": null,
      "yaps_all": null
    },
    {
      "id": 21215517,
      "name": "Adam Westerén",
      "rank": 30,
      "user_id": "-1",
      "topic_id": "INTEGRA",
      "username": "Wezaverse",
      "mindshare": 0.81,
      "projectId": 248,
      "duration": "7D",
      "updatedAt": 1760702633694,
      "follower_count": 9819,
      "smart_follower_count": 176,
      "insightfullness": null,
      "originality": null,
      "yaps_all": 524.24
    },
    {
      "id": 21215518,
      "name": "telan_eth",
      "rank": 31,
      "user_id": "-1",
      "topic_id": "INTEGRA",
      "username": "0xtelan_",
      "mindshare": 0.75,
      "projectId": 248,
      "duration": "7D",
      "updatedAt": 1760702633694,
      "follower_count": 1335,
      "smart_follower_count": 16,
      "insightfullness": null,
      "originality": null,
      "yaps_all": 12.13
    },
    {
      "id": 21215519,
      "name": "Haris Ali (mainnet arc)",
      "rank": 32,
      "user_id": "-1",
      "topic_id": "INTEGRA",
      "username": "Web3_Exper_t",
      "mindshare": 0.74,
      "projectId": 248,
      "duration": "7D",
      "updatedAt": 1760702633694,
      "follower_count": 3767,
      "smart_follower_count": 40,
      "insightfullness": null,
      "originality": null,
      "yaps_all": 92.61
    },
    {
      "id": 21215520,
      "name": "Panchu",
      "rank": 33,
      "user_id": "-1",
      "topic_id": "INTEGRA",
      "username": "Panchu2605",
      "mindshare": 0.73,
      "projectId": 248,
      "duration": "7D",
      "updatedAt": 1760702633694,
      "follower_count": 3536,
      "smart_follower_count": 11,
      "insightfullness": null,
      "originality": null,
      "yaps_all": 74.93
    },
    {
      "id": 21215521,
      "name": "Dr. Ray",
      "rank": 34,
      "user_id": "-1",
      "topic_id": "INTEGRA",
      "username": "Dr_Ray12",
      "mindshare": 0.72,
      "projectId": 248,
      "duration": "7D",
      "updatedAt": 1760702633694,
      "follower_count": 2930,
      "smart_follower_count": 18,
      "insightfullness": null,
      "originality": null,
      "yaps_all": 31.47
    },
    {
      "id": 21215522,
      "name": "TECA",
      "rank": 35,
      "user_id": "-1",
      "topic_id": "INTEGRA",
      "username": "CryptoTeca__",
      "mindshare": 0.72,
      "projectId": 248,
      "duration": "7D",
      "updatedAt": 1760702633694,
      "follower_count": 189829,
      "smart_follower_count": 70,
      "insightfullness": null,
      "originality": null,
      "yaps_all": null
    },
    {
      "id": 21215523,
      "name": "동굴 Ⓜ️Ⓜ️T",
      "rank": 36,
      "user_id": "-1",
      "topic_id": "INTEGRA",
      "username": "donggooori",
      "mindshare": 0.69,
      "projectId": 248,
      "duration": "7D",
      "updatedAt": 1760702633694,
      "follower_count": 898,
      "smart_follower_count": 7,
      "insightfullness": null,
      "originality": null,
      "yaps_all": null
    },
    {
      "id": 21215524,
      "name": "Amaris",
      "rank": 37,
      "user_id": "-1",
      "topic_id": "INTEGRA",
      "username": "amarisazuki",
      "mindshare": 0.68,
      "projectId": 248,
      "duration": "7D",
      "updatedAt": 1760702633694,
      "follower_count": 22945,
      "smart_follower_count": 80,
      "insightfullness": null,
      "originality": null,
      "yaps_all": null
    },
    {
      "id": 21215525,
      "name": "ZORD CRYPT",
      "rank": 38,
      "user_id": "-1",
      "topic_id": "INTEGRA",
      "username": "zordcrypt",
      "mindshare": 0.67,
      "projectId": 248,
      "duration": "7D",
      "updatedAt": 1760702633694,
      "follower_count": 27907,
      "smart_follower_count": 115,
      "insightfullness": null,
      "originality": null,
      "yaps_all": 307.73
    },
    {
      "id": 21215526,
      "name": "tochukwu",
      "rank": 39,
      "user_id": "-1",
      "topic_id": "INTEGRA",
      "username": "radar2122",
      "mindshare": 0.66,
      "projectId": 248,
      "duration": "7D",
      "updatedAt": 1760702633694,
      "follower_count": 2523,
      "smart_follower_count": 5,
      "insightfullness": null,
      "originality": null,
      "yaps_all": 1.88
    },
    {
      "id": 21215527,
      "name": "Captain Kent | 船长 🪶",
      "rank": 40,
      "user_id": "-1",
      "topic_id": "INTEGRA",
      "username": "captain_kent",
      "mindshare": 0.65,
      "projectId": 248,
      "duration": "7D",
      "updatedAt": 1760702633694,
      "follower_count": 7800,
      "smart_follower_count": 87,
      "insightfullness": null,
      "originality": null,
      "yaps_all": 357.2
    },
    {
      "id": 21215528,
      "name": "미토 meeto | Ⓜ️Ⓜ️T (✧ᴗ✧) ❖,❖",
      "rank": 41,
      "user_id": "-1",
      "topic_id": "INTEGRA",
      "username": "teemomeeto",
      "mindshare": 0.65,
      "projectId": 248,
      "duration": "7D",
      "updatedAt": 1760702633694,
      "follower_count": 2144,
      "smart_follower_count": 47,
      "insightfullness": null,
      "originality": null,
      "yaps_all": 45.51
    },
    {
      "id": 21215529,
      "name": "DnxtGen",
      "rank": 42,
      "user_id": "-1",
      "topic_id": "INTEGRA",
      "username": "allen_mojekwu",
      "mindshare": 0.64,
      "projectId": 248,
      "duration": "7D",
      "updatedAt": 1760702633694,
      "follower_count": 5147,
      "smart_follower_count": 72,
      "insightfullness": null,
      "originality": null,
      "yaps_all": 112.77
    },
    {
      "id": 21215530,
      "name": "Awwal",
      "rank": 43,
      "user_id": "-1",
      "topic_id": "INTEGRA",
      "username": "AwwalM0",
      "mindshare": 0.64,
      "projectId": 248,
      "duration": "7D",
      "updatedAt": 1760702633694,
      "follower_count": 2692,
      "smart_follower_count": 10,
      "insightfullness": null,
      "originality": null,
      "yaps_all": null
    },
    {
      "id": 21215531,
      "name": "Kizito.esq",
      "rank": 44,
      "user_id": "-1",
      "topic_id": "INTEGRA",
      "username": "Kizito_esq",
      "mindshare": 0.64,
      "projectId": 248,
      "duration": "7D",
      "updatedAt": 1760702633694,
      "follower_count": 2332,
      "smart_follower_count": 12,
      "insightfullness": null,
      "originality": null,
      "yaps_all": 25.42
    },
    {
      "id": 21215532,
      "name": "Avocado168",
      "rank": 45,
      "user_id": "-1",
      "topic_id": "INTEGRA",
      "username": "alpukat168",
      "mindshare": 0.63,
      "projectId": 248,
      "duration": "7D",
      "updatedAt": 1760702633694,
      "follower_count": 572,
      "smart_follower_count": 2,
      "insightfullness": null,
      "originality": null,
      "yaps_all": 17.44
    },
    {
      "id": 21215533,
      "name": "DEFI PRINCESS 「 🧬 」.",
      "rank": 46,
      "user_id": "-1",
      "topic_id": "INTEGRA",
      "username": "fancy0523",
      "mindshare": 0.63,
      "projectId": 248,
      "duration": "7D",
      "updatedAt": 1760702633694,
      "follower_count": 1893,
      "smart_follower_count": 11,
      "insightfullness": null,
      "originality": null,
      "yaps_all": 11.8
    },
    {
      "id": 21215534,
      "name": "Emalio_10 ^_^",
      "rank": 47,
      "user_id": "-1",
      "topic_id": "INTEGRA",
      "username": "Emalio_10",
      "mindshare": 0.59,
      "projectId": 248,
      "duration": "7D",
      "updatedAt": 1760702633694,
      "follower_count": 1489,
      "smart_follower_count": 6,
      "insightfullness": null,
      "originality": null,
      "yaps_all": null
    },
    {
      "id": 21215535,
      "name": "gt🔮🌊",
      "rank": 48,
      "user_id": "-1",
      "topic_id": "INTEGRA",
      "username": "gtofweb3",
      "mindshare": 0.57,
      "projectId": 248,
      "duration": "7D",
      "updatedAt": 1760702633694,
      "follower_count": 3040,
      "smart_follower_count": 24,
      "insightfullness": null,
      "originality": null,
      "yaps_all": 14.47
    },
    {
      "id": 21215536,
      "name": "Trust_MeⓂ️Ⓜ️T",
      "rank": 49,
      "user_id": "-1",
      "topic_id": "INTEGRA",
      "username": "Trust_mit",
      "mindshare": 0.56,
      "projectId": 248,
      "duration": "7D",
      "updatedAt": 1760702633694,
      "follower_count": 2956,
      "smart_follower_count": 81,
      "insightfullness": null,
      "originality": null,
      "yaps_all": 23.02
    },
    {
      "id": 21215537,
      "name": "RASTA🏌🏿‍♂️",
      "rank": 50,
      "user_id": "-1",
      "topic_id": "INTEGRA",
      "username": "Tundeffs_",
      "mindshare": 0.53,
      "projectId": 248,
      "duration": "7D",
      "updatedAt": 1760702633694,
      "follower_count": 2310,
      "smart_follower_count": 10,
      "insightfullness": null,
      "originality": null,
      "yaps_all": 27.6
    },
    {
      "id": 21215538,
      "name": "HAYLΞS.eth ➕",
      "rank": 51,
      "user_id": "-1",
      "topic_id": "INTEGRA",
      "username": "Haylesdefi",
      "mindshare": 0.53,
      "projectId": 248,
      "duration": "7D",
      "updatedAt": 1760702633694,
      "follower_count": 44860,
      "smart_follower_count": 210,
      "insightfullness": null,
      "originality": null,
      "yaps_all": null
    },
    {
      "id": 21215539,
      "name": "LukeⓂ️Ⓜ️T 🌸",
      "rank": 52,
      "user_id": "-1",
      "topic_id": "INTEGRA",
      "username": "0xblackluke",
      "mindshare": 0.52,
      "projectId": 248,
      "duration": "7D",
      "updatedAt": 1760702633694,
      "follower_count": 2371,
      "smart_follower_count": 49,
      "insightfullness": null,
      "originality": null,
      "yaps_all": 32.21
    },
    {
      "id": 21215540,
      "name": "TmT bear",
      "rank": 53,
      "user_id": "-1",
      "topic_id": "INTEGRA",
      "username": "IjeongU68167",
      "mindshare": 0.52,
      "projectId": 248,
      "duration": "7D",
      "updatedAt": 1760702633694,
      "follower_count": 873,
      "smart_follower_count": 10,
      "insightfullness": null,
      "originality": null,
      "yaps_all": null
    },
    {
      "id": 21215541,
      "name": "Law 🐻⛓️",
      "rank": 54,
      "user_id": "-1",
      "topic_id": "INTEGRA",
      "username": "_dreallboy",
      "mindshare": 0.51,
      "projectId": 248,
      "duration": "7D",
      "updatedAt": 1760702633694,
      "follower_count": 4173,
      "smart_follower_count": 6,
      "insightfullness": null,
      "originality": null,
      "yaps_all": null
    },
    {
      "id": 21215542,
      "name": "nolja💜Ⓜ️Ⓜ️TㅣMOM",
      "rank": 55,
      "user_id": "-1",
      "topic_id": "INTEGRA",
      "username": "freepass5373",
      "mindshare": 0.51,
      "projectId": 248,
      "duration": "7D",
      "updatedAt": 1760702633694,
      "follower_count": 3310,
      "smart_follower_count": 90,
      "insightfullness": null,
      "originality": null,
      "yaps_all": 32.5
    },
    {
      "id": 21215543,
      "name": "Homie (smart follower)",
      "rank": 56,
      "user_id": "-1",
      "topic_id": "INTEGRA",
      "username": "homiekking",
      "mindshare": 0.51,
      "projectId": 248,
      "duration": "7D",
      "updatedAt": 1760702633694,
      "follower_count": 2427,
      "smart_follower_count": 17,
      "insightfullness": null,
      "originality": null,
      "yaps_all": null
    },
    {
      "id": 21215544,
      "name": "PAPITO",
      "rank": 57,
      "user_id": "-1",
      "topic_id": "INTEGRA",
      "username": "papito_dele",
      "mindshare": 0.5,
      "projectId": 248,
      "duration": "7D",
      "updatedAt": 1760702633694,
      "follower_count": 2104,
      "smart_follower_count": 24,
      "insightfullness": null,
      "originality": null,
      "yaps_all": null
    },
    {
      "id": 21215545,
      "name": "Airdrop Trail",
      "rank": 58,
      "user_id": "-1",
      "topic_id": "INTEGRA",
      "username": "AirdropTrail",
      "mindshare": 0.5,
      "projectId": 248,
      "duration": "7D",
      "updatedAt": 1760702633694,
      "follower_count": 3475,
      "smart_follower_count": 33,
      "insightfullness": null,
      "originality": null,
      "yaps_all": 109.85
    },
    {
      "id": 21215546,
      "name": "수비짱 Ⓜ️Ⓜ️T",
      "rank": 59,
      "user_id": "-1",
      "topic_id": "INTEGRA",
      "username": "subijjjang",
      "mindshare": 0.49,
      "projectId": 248,
      "duration": "7D",
      "updatedAt": 1760702633694,
      "follower_count": 2196,
      "smart_follower_count": 55,
      "insightfullness": null,
      "originality": null,
      "yaps_all": 126.35
    },
    {
      "id": 21215547,
      "name": "하이바라",
      "rank": 60,
      "user_id": "-1",
      "topic_id": "INTEGRA",
      "username": "pizza1q2w3e",
      "mindshare": 0.45,
      "projectId": 248,
      "duration": "7D",
      "updatedAt": 1760702633694,
      "follower_count": 1502,
      "smart_follower_count": 19,
      "insightfullness": null,
      "originality": null,
      "yaps_all": null
    },
    {
      "id": 21215548,
      "name": "Vide Haldorsson",
      "rank": 61,
      "user_id": "-1",
      "topic_id": "INTEGRA",
      "username": "VideHaldorsson",
      "mindshare": 0.43,
      "projectId": 248,
      "duration": "7D",
      "updatedAt": 1760702633694,
      "follower_count": 4151,
      "smart_follower_count": 86,
      "insightfullness": null,
      "originality": null,
      "yaps_all": 2197.08
    },
    {
      "id": 21215549,
      "name": "Aryan",
      "rank": 62,
      "user_id": "-1",
      "topic_id": "INTEGRA",
      "username": "Aryanbabariy",
      "mindshare": 0.41,
      "projectId": 248,
      "duration": "7D",
      "updatedAt": 1760702633694,
      "follower_count": 841,
      "smart_follower_count": 26,
      "insightfullness": null,
      "originality": null,
      "yaps_all": null
    },
    {
      "id": 21215550,
      "name": "S𝐚𝐢𝐧𝐭G𝖊𝖗𝖆𝖑d🧧",
      "rank": 63,
      "user_id": "-1",
      "topic_id": "INTEGRA",
      "username": "TweetByGerald",
      "mindshare": 0.41,
      "projectId": 248,
      "duration": "7D",
      "updatedAt": 1760702633694,
      "follower_count": 37484,
      "smart_follower_count": 122,
      "insightfullness": null,
      "originality": null,
      "yaps_all": 275.95
    },
    {
      "id": 21215551,
      "name": "산할Ⓜ️Ⓜ️T",
      "rank": 64,
      "user_id": "-1",
      "topic_id": "INTEGRA",
      "username": "AGeullo",
      "mindshare": 0.39,
      "projectId": 248,
      "duration": "7D",
      "updatedAt": 1760702633694,
      "follower_count": 3115,
      "smart_follower_count": 72,
      "insightfullness": null,
      "originality": null,
      "yaps_all": 38.83
    },
    {
      "id": 21215552,
      "name": "Ace Crypt",
      "rank": 65,
      "user_id": "-1",
      "topic_id": "INTEGRA",
      "username": "ace3tech",
      "mindshare": 0.39,
      "projectId": 248,
      "duration": "7D",
      "updatedAt": 1760702633694,
      "follower_count": 2304,
      "smart_follower_count": 11,
      "insightfullness": null,
      "originality": null,
      "yaps_all": null
    },
    {
      "id": 21215553,
      "name": "~0xOlami 👨‍🌾🖤",
      "rank": 66,
      "user_id": "-1",
      "topic_id": "INTEGRA",
      "username": "Crypto0304",
      "mindshare": 0.38,
      "projectId": 248,
      "duration": "7D",
      "updatedAt": 1760702633694,
      "follower_count": 2789,
      "smart_follower_count": 14,
      "insightfullness": null,
      "originality": null,
      "yaps_all": 16.54
    },
    {
      "id": 21215554,
      "name": "0xMistBlade 🗡️",
      "rank": 67,
      "user_id": "-1",
      "topic_id": "INTEGRA",
      "username": "0xMistBlade",
      "mindshare": 0.37,
      "projectId": 248,
      "duration": "7D",
      "updatedAt": 1760702633694,
      "follower_count": 43555,
      "smart_follower_count": 1152,
      "insightfullness": null,
      "originality": null,
      "yaps_all": 846.93
    },
    {
      "id": 21215555,
      "name": "Lucifer| 🕊️🌌",
      "rank": 68,
      "user_id": "-1",
      "topic_id": "INTEGRA",
      "username": "GNftarmy",
      "mindshare": 0.37,
      "projectId": 248,
      "duration": "7D",
      "updatedAt": 1760702633694,
      "follower_count": 1584,
      "smart_follower_count": 16,
      "insightfullness": null,
      "originality": null,
      "yaps_all": 13.86
    },
    {
      "id": 21215556,
      "name": "DrstrangE",
      "rank": 69,
      "user_id": "-1",
      "topic_id": "INTEGRA",
      "username": "DCHELSFC1",
      "mindshare": 0.37,
      "projectId": 248,
      "duration": "7D",
      "updatedAt": 1760702633694,
      "follower_count": 3594,
      "smart_follower_count": 8,
      "insightfullness": null,
      "originality": null,
      "yaps_all": 22.52
    },
    {
      "id": 21215557,
      "name": "alphabatkim Ⓜ️Ⓜ️T",
      "rank": 70,
      "user_id": "-1",
      "topic_id": "INTEGRA",
      "username": "alphabatkim",
      "mindshare": 0.36,
      "projectId": 248,
      "duration": "7D",
      "updatedAt": 1760702633694,
      "follower_count": 3232,
      "smart_follower_count": 73,
      "insightfullness": null,
      "originality": null,
      "yaps_all": 43.16
    },
    {
      "id": 21215558,
      "name": "ＣｒｙｐｔｏＡｍｉｒＸ",
      "rank": 71,
      "user_id": "-1",
      "topic_id": "INTEGRA",
      "username": "Amirirh1",
      "mindshare": 0.36,
      "projectId": 248,
      "duration": "7D",
      "updatedAt": 1760702633694,
      "follower_count": 2387,
      "smart_follower_count": 14,
      "insightfullness": null,
      "originality": null,
      "yaps_all": null
    },
    {
      "id": 21215559,
      "name": "서우",
      "rank": 72,
      "user_id": "-1",
      "topic_id": "INTEGRA",
      "username": "roti_airdrop",
      "mindshare": 0.35,
      "projectId": 248,
      "duration": "7D",
      "updatedAt": 1760702633694,
      "follower_count": 2805,
      "smart_follower_count": 28,
      "insightfullness": null,
      "originality": null,
      "yaps_all": 37.65
    },
    {
      "id": 21215560,
      "name": "Kosmozilla",
      "rank": 73,
      "user_id": "-1",
      "topic_id": "INTEGRA",
      "username": "0xKosmozilla",
      "mindshare": 0.33,
      "projectId": 248,
      "duration": "7D",
      "updatedAt": 1760702633694,
      "follower_count": 321,
      "smart_follower_count": 4,
      "insightfullness": null,
      "originality": null,
      "yaps_all": null
    },
    {
      "id": 21215561,
      "name": "Berry 🍓",
      "rank": 74,
      "user_id": "-1",
      "topic_id": "INTEGRA",
      "username": "Berry_Sooll",
      "mindshare": 0.32,
      "projectId": 248,
      "duration": "7D",
      "updatedAt": 1760702633694,
      "follower_count": 1772,
      "smart_follower_count": 46,
      "insightfullness": null,
      "originality": null,
      "yaps_all": 260.55
    },
    {
      "id": 21215562,
      "name": "Navarro",
      "rank": 75,
      "user_id": "-1",
      "topic_id": "INTEGRA",
      "username": "LT_Navarro",
      "mindshare": 0.32,
      "projectId": 248,
      "duration": "7D",
      "updatedAt": 1760702633694,
      "follower_count": 1837,
      "smart_follower_count": 10,
      "insightfullness": null,
      "originality": null,
      "yaps_all": 10.87
    },
    {
      "id": 21215563,
      "name": "ruin3196🦅🟠",
      "rank": 76,
      "user_id": "-1",
      "topic_id": "INTEGRA",
      "username": "ruin3196",
      "mindshare": 0.31,
      "projectId": 248,
      "duration": "7D",
      "updatedAt": 1760702633694,
      "follower_count": 1909,
      "smart_follower_count": 54,
      "insightfullness": null,
      "originality": null,
      "yaps_all": 18.93
    },
    {
      "id": 21215564,
      "name": "OK👑",
      "rank": 77,
      "user_id": "-1",
      "topic_id": "INTEGRA",
      "username": "OKcrpt",
      "mindshare": 0.31,
      "projectId": 248,
      "duration": "7D",
      "updatedAt": 1760702633694,
      "follower_count": 1700,
      "smart_follower_count": 3,
      "insightfullness": null,
      "originality": null,
      "yaps_all": null
    },
    {
      "id": 21215565,
      "name": "bee (❖,❖)",
      "rank": 78,
      "user_id": "-1",
      "topic_id": "INTEGRA",
      "username": "emrizblaq",
      "mindshare": 0.3,
      "projectId": 248,
      "duration": "7D",
      "updatedAt": 1760702633694,
      "follower_count": 8617,
      "smart_follower_count": 76,
      "insightfullness": null,
      "originality": null,
      "yaps_all": null
    },
    {
      "id": 21215566,
      "name": "131",
      "rank": 79,
      "user_id": "-1",
      "topic_id": "INTEGRA",
      "username": "iK0rede",
      "mindshare": 0.3,
      "projectId": 248,
      "duration": "7D",
      "updatedAt": 1760702633694,
      "follower_count": 9108,
      "smart_follower_count": 78,
      "insightfullness": null,
      "originality": null,
      "yaps_all": 260.01
    },
    {
      "id": 21215567,
      "name": "leeyong.ip (✧ᴗ✧) Ⓜ️Ⓜ️T",
      "rank": 80,
      "user_id": "-1",
      "topic_id": "INTEGRA",
      "username": "yo565678",
      "mindshare": 0.3,
      "projectId": 248,
      "duration": "7D",
      "updatedAt": 1760702633694,
      "follower_count": 2053,
      "smart_follower_count": 51,
      "insightfullness": null,
      "originality": null,
      "yaps_all": 46.27
    },
    {
      "id": 21215568,
      "name": "Solaceeeeee🪐",
      "rank": 81,
      "user_id": "-1",
      "topic_id": "INTEGRA",
      "username": "solace_okere",
      "mindshare": 0.3,
      "projectId": 248,
      "duration": "7D",
      "updatedAt": 1760702633694,
      "follower_count": 5260,
      "smart_follower_count": 23,
      "insightfullness": null,
      "originality": null,
      "yaps_all": 134.32
    },
    {
      "id": 21215569,
      "name": "ßsæmmyFX \\\\",
      "rank": 82,
      "user_id": "-1",
      "topic_id": "INTEGRA",
      "username": "GeeNwachi83785",
      "mindshare": 0.29,
      "projectId": 248,
      "duration": "7D",
      "updatedAt": 1760702633694,
      "follower_count": 1459,
      "smart_follower_count": 2,
      "insightfullness": null,
      "originality": null,
      "yaps_all": null
    },
    {
      "id": 21215570,
      "name": "람쥐썬더 Ramz MOM Ⓜ️Ⓜ️T",
      "rank": 83,
      "user_id": "-1",
      "topic_id": "INTEGRA",
      "username": "ramztd",
      "mindshare": 0.29,
      "projectId": 248,
      "duration": "7D",
      "updatedAt": 1760702633694,
      "follower_count": 2768,
      "smart_follower_count": 103,
      "insightfullness": null,
      "originality": null,
      "yaps_all": 148.66
    },
    {
      "id": 21215571,
      "name": "人在币圈（Lovecity） (小爱)🦅🟠 $FF",
      "rank": 84,
      "user_id": "-1",
      "topic_id": "INTEGRA",
      "username": "lovecity0088",
      "mindshare": 0.29,
      "projectId": 248,
      "duration": "7D",
      "updatedAt": 1760702633694,
      "follower_count": 8278,
      "smart_follower_count": 91,
      "insightfullness": null,
      "originality": null,
      "yaps_all": 377.58
    },
    {
      "id": 21215572,
      "name": "Hosen",
      "rank": 85,
      "user_id": "-1",
      "topic_id": "INTEGRA",
      "username": "Hossein_esv",
      "mindshare": 0.29,
      "projectId": 248,
      "duration": "7D",
      "updatedAt": 1760702633694,
      "follower_count": 2631,
      "smart_follower_count": 24,
      "insightfullness": null,
      "originality": null,
      "yaps_all": 0.87
    },
    {
      "id": 21215573,
      "name": "Bigkay",
      "rank": 86,
      "user_id": "-1",
      "topic_id": "INTEGRA",
      "username": "Big_kayyyyyyyy",
      "mindshare": 0.29,
      "projectId": 248,
      "duration": "7D",
      "updatedAt": 1760702633694,
      "follower_count": 869,
      "smart_follower_count": 2,
      "insightfullness": null,
      "originality": null,
      "yaps_all": null
    },
    {
      "id": 21215574,
      "name": "ChyChyTheMagnificent (✧ᴗ✧)",
      "rank": 87,
      "user_id": "-1",
      "topic_id": "INTEGRA",
      "username": "chychyorjhy",
      "mindshare": 0.28,
      "projectId": 248,
      "duration": "7D",
      "updatedAt": 1760702633694,
      "follower_count": 1193,
      "smart_follower_count": 10,
      "insightfullness": null,
      "originality": null,
      "yaps_all": 4.1
    },
    {
      "id": 21215575,
      "name": "한별이 Ⓜ️Ⓜ️T",
      "rank": 88,
      "user_id": "-1",
      "topic_id": "INTEGRA",
      "username": "CHUNWON1155",
      "mindshare": 0.27,
      "projectId": 248,
      "duration": "7D",
      "updatedAt": 1760702633694,
      "follower_count": 2607,
      "smart_follower_count": 57,
      "insightfullness": null,
      "originality": null,
      "yaps_all": 62.45
    },
    {
      "id": 21215576,
      "name": "Sunrise 🌅",
      "rank": 89,
      "user_id": "-1",
      "topic_id": "INTEGRA",
      "username": "Man_3hunting",
      "mindshare": 0.27,
      "projectId": 248,
      "duration": "7D",
      "updatedAt": 1760702633694,
      "follower_count": 1937,
      "smart_follower_count": 3,
      "insightfullness": null,
      "originality": null,
      "yaps_all": 1.24
    },
    {
      "id": 21215577,
      "name": "Waqas",
      "rank": 90,
      "user_id": "-1",
      "topic_id": "INTEGRA",
      "username": "WaqasCryptoHub",
      "mindshare": 0.26,
      "projectId": 248,
      "duration": "7D",
      "updatedAt": 1760702633694,
      "follower_count": 3146,
      "smart_follower_count": 48,
      "insightfullness": null,
      "originality": null,
      "yaps_all": 76.49
    },
    {
      "id": 21215578,
      "name": "deniyi",
      "rank": 91,
      "user_id": "-1",
      "topic_id": "INTEGRA",
      "username": "BiggestN_",
      "mindshare": 0.26,
      "projectId": 248,
      "duration": "7D",
      "updatedAt": 1760702633694,
      "follower_count": 1014,
      "smart_follower_count": 2,
      "insightfullness": null,
      "originality": null,
      "yaps_all": null
    },
    {
      "id": 21215579,
      "name": "RUNDEM!",
      "rank": 92,
      "user_id": "-1",
      "topic_id": "INTEGRA",
      "username": "rundem01",
      "mindshare": 0.25,
      "projectId": 248,
      "duration": "7D",
      "updatedAt": 1760702633694,
      "follower_count": 2221,
      "smart_follower_count": 5,
      "insightfullness": null,
      "originality": null,
      "yaps_all": null
    },
    {
      "id": 21215580,
      "name": "Bruno Jr Talent Ⓜ️Ⓜ️T (Ø,G)",
      "rank": 93,
      "user_id": "-1",
      "topic_id": "INTEGRA",
      "username": "bruno_jr_talent",
      "mindshare": 0.24,
      "projectId": 248,
      "duration": "7D",
      "updatedAt": 1760702633694,
      "follower_count": 1836,
      "smart_follower_count": 9,
      "insightfullness": null,
      "originality": null,
      "yaps_all": null
    },
    {
      "id": 21215581,
      "name": "Victor ig",
      "rank": 94,
      "user_id": "-1",
      "topic_id": "INTEGRA",
      "username": "Victor_igho_",
      "mindshare": 0.23,
      "projectId": 248,
      "duration": "7D",
      "updatedAt": 1760702633694,
      "follower_count": 2778,
      "smart_follower_count": 11,
      "insightfullness": null,
      "originality": null,
      "yaps_all": null
    },
    {
      "id": 21215582,
      "name": "Ghost👻 | NOYA",
      "rank": 95,
      "user_id": "-1",
      "topic_id": "INTEGRA",
      "username": "RealHope01_",
      "mindshare": 0.23,
      "projectId": 248,
      "duration": "7D",
      "updatedAt": 1760702633694,
      "follower_count": 1175,
      "smart_follower_count": 3,
      "insightfullness": null,
      "originality": null,
      "yaps_all": null
    },
    {
      "id": 21215583,
      "name": "AMEERAH",
      "rank": 96,
      "user_id": "-1",
      "topic_id": "INTEGRA",
      "username": "MEERAHTHAGREAT",
      "mindshare": 0.22,
      "projectId": 248,
      "duration": "7D",
      "updatedAt": 1760702633694,
      "follower_count": 1831,
      "smart_follower_count": 11,
      "insightfullness": null,
      "originality": null,
      "yaps_all": null
    },
    {
      "id": 21215584,
      "name": "Yashuleo",
      "rank": 97,
      "user_id": "-1",
      "topic_id": "INTEGRA",
      "username": "yashuleo1",
      "mindshare": 0.22,
      "projectId": 248,
      "duration": "7D",
      "updatedAt": 1760702633694,
      "follower_count": 3113,
      "smart_follower_count": 19,
      "insightfullness": null,
      "originality": null,
      "yaps_all": 36.14
    },
    {
      "id": 21215585,
      "name": "Damii (✧ᴗ✧)",
      "rank": 98,
      "user_id": "-1",
      "topic_id": "INTEGRA",
      "username": "davidswrld_x",
      "mindshare": 0.21,
      "projectId": 248,
      "duration": "7D",
      "updatedAt": 1760702633694,
      "follower_count": 1491,
      "smart_follower_count": 13,
      "insightfullness": null,
      "originality": null,
      "yaps_all": 3.53
    },
    {
      "id": 21215586,
      "name": "BiGShaZ💀 (❖,❖)",
      "rank": 99,
      "user_id": "-1",
      "topic_id": "INTEGRA",
      "username": "Shasisco01",
      "mindshare": 0.21,
      "projectId": 248,
      "duration": "7D",
      "updatedAt": 1760702633694,
      "follower_count": 965,
      "smart_follower_count": 29,
      "insightfullness": null,
      "originality": null,
      "yaps_all": null
    },
    {
      "id": 21215587,
      "name": "ZËK💎",
      "rank": 100,
      "user_id": "-1",
      "topic_id": "INTEGRA",
      "username": "Gbemzy67",
      "mindshare": 0.2,
      "projectId": 248,
      "duration": "7D",
      "updatedAt": 1760702633694,
      "follower_count": 1301,
      "smart_follower_count": 5,
      "insightfullness": null,
      "originality": null,
      "yaps_all": null
    }
  ]
}