{
  "user": "_nityas",
  "timeframes": {
    "7D": {
      "miden": [
        {
          "t": 1763424102447,
          "mindshare": 0.73
        },
        {
          "t": 1763463916461,
          "mindshare": 0.7
        }
      ]
    },
    "30D": {
      "miden": [
        {
          "t": 1763424108579,
          "mindshare": 0.44
        },
        {
          "t": 1763463922852,
          "mindshare": 0.43
        },
        {
          "t": 1763723927320,
          "mindshare": 0.37
        },
        {
          "t": 1763770397991,
          "mindshare": 0.36
        },
        {
          "t": 1763809560852,
          "mindshare": 0.36
        },
        {
          "t": 1763857186211,
          "mindshare": 0.35
        },
        {
          "t": 1763896911268,
          "mindshare": 0.34
        },
        {
          "t": 1763944072044,
          "mindshare": 0.33
        },
        {
          "t": 1763985113444,
          "mindshare": 0.33
        },
        {
          "t": 1764031806680,
          "mindshare": 0.32
        },
        {
          "t": 1764072368865,
          "mindshare": 0.31
        },
        {
          "t": 1764112426985,
          "mindshare": 0.31
        },
        {
          "t": 1764152860647,
          "mindshare": 0.3
        },
        {
          "t": 1764201309245,
          "mindshare": 0.3
        }
      ]
    }
  }
}