{
  "user": "joyjoyflyz",
  "timeframes": {
    "7D": {
      "edgen": [
        {
          "t": 1766478440460,
          "mindshare": 1.0
        },
        {
          "t": 1766519891231,
          "mindshare": 0.93
        },
        {
          "t": 1766560770128,
          "mindshare": 0.85
        },
        {
          "t": 1766602171653,
          "mindshare": 0.67
        }
      ],
      "kindred": [
        {
          "t": 1766651204859,
          "mindshare": 0.31
        }
      ]
    },
    "30D": {
      "edgen": [
        {
          "t": 1766478446824,
          "mindshare": 0.34
        },
        {
          "t": 1766519899638,
          "mindshare": 0.34
        },
        {
          "t": 1766560776957,
          "mindshare": 0.35
        },
        {
          "t": 1766602179904,
          "mindshare": 0.35
        },
        {
          "t": 1766651583765,
          "mindshare": 0.35
        }
      ]
    }
  }
}