{
  "user": "maxwellwillss",
  "timeframes": {
    "7D": {
      "goatnetwork": [
        {
          "t": 1766157938500,
          "mindshare": 0.34
        },
        {
          "t": 1766274513536,
          "mindshare": 0.36
        },
        {
          "t": 1766317743276,
          "mindshare": 0.36
        },
        {
          "t": 1766361203555,
          "mindshare": 0.37
        },
        {
          "t": 1766387595850,
          "mindshare": 0.38
        },
        {
          "t": 1766444449917,
          "mindshare": 0.39
        },
        {
          "t": 1766474041637,
          "mindshare": 0.4
        }
      ]
    }
  }
}