{
  "data": [
    {
      "id": 3820528,
      "name": "Marc | Pyth 🔮",
      "rank": 1,
      "user_id": null,
      "topic_id": "PYTH",
      "username": "KemarTiti",
      "mindshare": 7.2,
      "projectId": 36,
      "duration": "30D",
      "updatedAt": 1766362713830,
      "follower_count": 5950,
      "smart_follower_count": 536,
      "insightfullness": null,
      "originality": null,
      "yaps_all": null
    },
    {
      "id": 3820529,
      "name": "Mike Cahill | Pyth🔮",
      "rank": 2,
      "user_id": null,
      "topic_id": "PYTH",
      "username": "mdomcahill",
      "mindshare": 5.88,
      "projectId": 36,
      "duration": "30D",
      "updatedAt": 1766362713830,
      "follower_count": 9244,
      "smart_follower_count": 623,
      "insightfullness": null,
      "originality": null,
      "yaps_all": null
    },
    {
      "id": 3820530,
      "name": "Pierre I Pyth 🔮",
      "rank": 3,
      "user_id": null,
      "topic_id": "PYTH",
      "username": "realpepito",
      "mindshare": 5.45,
      "projectId": 36,
      "duration": "30D",
      "updatedAt": 1766362713830,
      "follower_count": 6945,
      "smart_follower_count": 269,
      "insightfullness": null,
      "originality": null,
      "yaps_all": null
    },
    {
      "id": 3820531,
      "name": "Peter",
      "rank": 4,
      "user_id": null,
      "topic_id": "PYTH",
      "username": "realpeterjm",
      "mindshare": 3.81,
      "projectId": 36,
      "duration": "30D",
      "updatedAt": 1766362713830,
      "follower_count": 8350,
      "smart_follower_count": 566,
      "insightfullness": null,
      "originality": null,
      "yaps_all": null
    },
    {
      "id": 3820532,
      "name": "Matt (SEDA is NOT an Oracle)",
      "rank": 5,
      "user_id": null,
      "topic_id": "PYTH",
      "username": "Mat_Oracle",
      "mindshare": 2.94,
      "projectId": 36,
      "duration": "30D",
      "updatedAt": 1766362713830,
      "follower_count": 2145,
      "smart_follower_count": 133,
      "insightfullness": null,
      "originality": null,
      "yaps_all": null
    },
    {
      "id": 3820533,
      "name": "Genia🔮",
      "rank": 6,
      "user_id": null,
      "topic_id": "PYTH",
      "username": "Genia_XBT",
      "mindshare": 2.43,
      "projectId": 36,
      "duration": "30D",
      "updatedAt": 1766362713830,
      "follower_count": 6958,
      "smart_follower_count": 486,
      "insightfullness": null,
      "originality": null,
      "yaps_all": null
    },
    {
      "id": 3820534,
      "name": "zerokn0wledge.hl 🪬✨",
      "rank": 7,
      "user_id": null,
      "topic_id": "PYTH",
      "username": "zerokn0wledge_",
      "mindshare": 1.62,
      "projectId": 36,
      "duration": "30D",
      "updatedAt": 1766362713830,
      "follower_count": 26902,
      "smart_follower_count": 981,
      "insightfullness": null,
      "originality": null,
      "yaps_all": null
    },
    {
      "id": 3820535,
      "name": "Planck 🔮",
      "rank": 8,
      "user_id": null,
      "topic_id": "PYTH",
      "username": "hopheycaptain",
      "mindshare": 1.61,
      "projectId": 36,
      "duration": "30D",
      "updatedAt": 1766362713830,
      "follower_count": 2482,
      "smart_follower_count": 72,
      "insightfullness": null,
      "originality": null,
      "yaps_all": null
    },
    {
      "id": 3820536,
      "name": "Chop 🦈🔮",
      "rank": 9,
      "user_id": null,
      "topic_id": "PYTH",
      "username": "CHOPPAtheSHARK",
      "mindshare": 1.54,
      "projectId": 36,
      "duration": "30D",
      "updatedAt": 1766362713830,
      "follower_count": 4128,
      "smart_follower_count": 175,
      "insightfullness": null,
      "originality": null,
      "yaps_all": null
    },
    {
      "id": 3820537,
      "name": "币圈荒木｜Araki🪵",
      "rank": 10,
      "user_id": null,
      "topic_id": "PYTH",
      "username": "HM010169",
      "mindshare": 1.28,
      "projectId": 36,
      "duration": "30D",
      "updatedAt": 1766362713830,
      "follower_count": 126439,
      "smart_follower_count": 348,
      "insightfullness": null,
      "originality": null,
      "yaps_all": 1346.28
    },
    {
      "id": 3820538,
      "name": "Pukerainbow 🤮🌈",
      "rank": 11,
      "user_id": null,
      "topic_id": "PYTH",
      "username": "pukerrainbrow",
      "mindshare": 1.24,
      "projectId": 36,
      "duration": "30D",
      "updatedAt": 1766362713830,
      "follower_count": 79879,
      "smart_follower_count": 1068,
      "insightfullness": null,
      "originality": null,
      "yaps_all": 1693.47
    },
    {
      "id": 3820539,
      "name": "CryptoMaid加密女仆お嬢様 .edge🦭",
      "rank": 12,
      "user_id": null,
      "topic_id": "PYTH",
      "username": "maid_crypto",
      "mindshare": 0.89,
      "projectId": 36,
      "duration": "30D",
      "updatedAt": 1766362713830,
      "follower_count": 137783,
      "smart_follower_count": 572,
      "insightfullness": null,
      "originality": null,
      "yaps_all": null
    },
    {
      "id": 52178970,
      "name": "AM Crypto",
      "rank": 13,
      "user_id": null,
      "topic_id": "PYTH",
      "username": "Aira_meca",
      "mindshare": 0.83,
      "projectId": 36,
      "duration": "30D",
      "updatedAt": 1766362713830,
      "follower_count": 1296,
      "smart_follower_count": 28,
      "insightfullness": null,
      "originality": null,
      "yaps_all": 406.74
    },
    {
      "id": 52227999,
      "name": "anymose.edge 🦭",
      "rank": 14,
      "user_id": null,
      "topic_id": "PYTH",
      "username": "anymose96",
      "mindshare": 0.59,
      "projectId": 36,
      "duration": "30D",
      "updatedAt": 1766362713830,
      "follower_count": 28594,
      "smart_follower_count": 558,
      "insightfullness": null,
      "originality": null,
      "yaps_all": 4952.34
    },
    {
      "id": 52228000,
      "name": "Leo.Master.MemeMax ⚡️",
      "rank": 15,
      "user_id": null,
      "topic_id": "PYTH",
      "username": "ezeroho8245",
      "mindshare": 0.58,
      "projectId": 36,
      "duration": "30D",
      "updatedAt": 1766362713830,
      "follower_count": 11590,
      "smart_follower_count": 128,
      "insightfullness": null,
      "originality": null,
      "yaps_all": 945.66
    },
    {
      "id": 52228001,
      "name": "Kira ✝️ ∞ KIN 🤖ボッ",
      "rank": 16,
      "user_id": null,
      "topic_id": "PYTH",
      "username": "nftkira_kr",
      "mindshare": 0.51,
      "projectId": 36,
      "duration": "30D",
      "updatedAt": 1766362713830,
      "follower_count": 19191,
      "smart_follower_count": 180,
      "insightfullness": null,
      "originality": null,
      "yaps_all": null
    },
    {
      "id": 52228002,
      "name": "good",
      "rank": 17,
      "user_id": null,
      "topic_id": "PYTH",
      "username": "thenarrator",
      "mindshare": 0.49,
      "projectId": 36,
      "duration": "30D",
      "updatedAt": 1766362713830,
      "follower_count": 100512,
      "smart_follower_count": 1161,
      "insightfullness": null,
      "originality": null,
      "yaps_all": null
    },
    {
      "id": 52228003,
      "name": "Djani",
      "rank": 18,
      "user_id": null,
      "topic_id": "PYTH",
      "username": "DjaniWhaleSkul",
      "mindshare": 0.48,
      "projectId": 36,
      "duration": "30D",
      "updatedAt": 1766362713830,
      "follower_count": 9131,
      "smart_follower_count": 192,
      "insightfullness": null,
      "originality": null,
      "yaps_all": 534.41
    },
    {
      "id": 52228004,
      "name": "BruceBlue 🌲",
      "rank": 19,
      "user_id": null,
      "topic_id": "PYTH",
      "username": "BruceBlue",
      "mindshare": 0.46,
      "projectId": 36,
      "duration": "30D",
      "updatedAt": 1766362713830,
      "follower_count": 4699,
      "smart_follower_count": 124,
      "insightfullness": null,
      "originality": null,
      "yaps_all": 374.1
    },
    {
      "id": 52228005,
      "name": "Shinkiro",
      "rank": 20,
      "user_id": null,
      "topic_id": "PYTH",
      "username": "ShinKiro14",
      "mindshare": 0.38,
      "projectId": 36,
      "duration": "30D",
      "updatedAt": 1766362713830,
      "follower_count": 1649,
      "smart_follower_count": 81,
      "insightfullness": null,
      "originality": null,
      "yaps_all": 903.93
    },
    {
      "id": 52228006,
      "name": "ALTF4",
      "rank": 21,
      "user_id": null,
      "topic_id": "PYTH",
      "username": "0xALTF4",
      "mindshare": 0.37,
      "projectId": 36,
      "duration": "30D",
      "updatedAt": 1766362713830,
      "follower_count": 60906,
      "smart_follower_count": 573,
      "insightfullness": null,
      "originality": null,
      "yaps_all": 1262.16
    },
    {
      "id": 52228007,
      "name": "bats4",
      "rank": 22,
      "user_id": null,
      "topic_id": "PYTH",
      "username": "bats4",
      "mindshare": 0.33,
      "projectId": 36,
      "duration": "30D",
      "updatedAt": 1766362713830,
      "follower_count": 1179,
      "smart_follower_count": 24,
      "insightfullness": null,
      "originality": null,
      "yaps_all": null
    },
    {
      "id": 52228008,
      "name": "Hyojin Cho l MemeMax⚡️",
      "rank": 23,
      "user_id": null,
      "topic_id": "PYTH",
      "username": "Maxi_cho",
      "mindshare": 0.25,
      "projectId": 36,
      "duration": "30D",
      "updatedAt": 1766362713830,
      "follower_count": 10342,
      "smart_follower_count": 219,
      "insightfullness": null,
      "originality": null,
      "yaps_all": 392.69
    },
    {
      "id": 52228009,
      "name": "무두서일기.MOODOO📚",
      "rank": 24,
      "user_id": null,
      "topic_id": "PYTH",
      "username": "MOODOO_Diary",
      "mindshare": 0.2,
      "projectId": 36,
      "duration": "30D",
      "updatedAt": 1766362713830,
      "follower_count": 13233,
      "smart_follower_count": 251,
      "insightfullness": null,
      "originality": null,
      "yaps_all": 1305.09
    },
    {
      "id": 52228010,
      "name": "코인추천요정 | GMB LABS",
      "rank": 25,
      "user_id": null,
      "topic_id": "PYTH",
      "username": "GMB_Coinangel",
      "mindshare": 0.09,
      "projectId": 36,
      "duration": "30D",
      "updatedAt": 1766362713830,
      "follower_count": 9076,
      "smart_follower_count": 150,
      "insightfullness": null,
      "originality": null,
      "yaps_all": null
    },
    {
      "id": 52228011,
      "name": "0xfarmed",
      "rank": 26,
      "user_id": null,
      "topic_id": "PYTH",
      "username": "0xfarmed",
      "mindshare": 0.08,
      "projectId": 36,
      "duration": "30D",
      "updatedAt": 1766362713830,
      "follower_count": 1817,
      "smart_follower_count": 71,
      "insightfullness": null,
      "originality": null,
      "yaps_all": null
    },
    {
      "id": 55759895,
      "name": "dONΞ✳️디온",
      "rank": 27,
      "user_id": null,
      "topic_id": "PYTH",
      "username": "dcrypto",
      "mindshare": 0.05,
      "projectId": 36,
      "duration": "30D",
      "updatedAt": 1766362713830,
      "follower_count": 5245,
      "smart_follower_count": 129,
      "insightfullness": null,
      "originality": null,
      "yaps_all": null
    }
  ]
}