{
  "data": [
    {
      "id": 74831,
      "name": "Christopher Kocurek",
      "rank": 1,
      "user_id": "-1",
      "topic_id": "DEFIAPP",
      "username": "bigironchris",
      "mindshare": 17.28,
      "projectId": 18,
      "duration": "7D",
      "updatedAt": 1763164792681,
      "follower_count": 10887,
      "smart_follower_count": 262,
      "insightfullness": null,
      "originality": null,
      "yaps_all": null
    },
    {
      "id": 74832,
      "name": "ᴛʀᴀᴄᴇʀ",
      "rank": 2,
      "user_id": "-1",
      "topic_id": "DEFIAPP",
      "username": "DeFiTracer",
      "mindshare": 12.25,
      "projectId": 18,
      "duration": "7D",
      "updatedAt": 1763164792681,
      "follower_count": 333949,
      "smart_follower_count": 493,
      "insightfullness": null,
      "originality": null,
      "yaps_all": null
    },
    {
      "id": 74833,
      "name": "JCRΞW //",
      "rank": 3,
      "user_id": "-1",
      "topic_id": "DEFIAPP",
      "username": "jcrew_eth",
      "mindshare": 7.16,
      "projectId": 18,
      "duration": "7D",
      "updatedAt": 1763164792681,
      "follower_count": 3616,
      "smart_follower_count": 244,
      "insightfullness": null,
      "originality": null,
      "yaps_all": null
    },
    {
      "id": 74834,
      "name": "0xBclub | 摸金校尉 🔶 BNB",
      "rank": 4,
      "user_id": "-1",
      "topic_id": "DEFIAPP",
      "username": "0xBclub",
      "mindshare": 6.28,
      "projectId": 18,
      "duration": "7D",
      "updatedAt": 1763164792681,
      "follower_count": 129852,
      "smart_follower_count": 384,
      "insightfullness": null,
      "originality": null,
      "yaps_all": null
    },
    {
      "id": 74835,
      "name": "CувєяWαяяισя",
      "rank": 5,
      "user_id": "-1",
      "topic_id": "DEFIAPP",
      "username": "Cyber_Warriorr",
      "mindshare": 5.93,
      "projectId": 18,
      "duration": "7D",
      "updatedAt": 1763164792681,
      "follower_count": 13414,
      "smart_follower_count": 156,
      "insightfullness": null,
      "originality": null,
      "yaps_all": null
    },
    {
      "id": 74836,
      "name": "乔帮主退休月球收租و 🌊RIVER Mememax⚡️ edge 🦭",
      "rank": 6,
      "user_id": "-1",
      "topic_id": "DEFIAPP",
      "username": "Joensmoon",
      "mindshare": 5.33,
      "projectId": 18,
      "duration": "7D",
      "updatedAt": 1763164792681,
      "follower_count": 24493,
      "smart_follower_count": 191,
      "insightfullness": null,
      "originality": null,
      "yaps_all": null
    },
    {
      "id": 74837,
      "name": "TK🎩",
      "rank": 7,
      "user_id": "-1",
      "topic_id": "DEFIAPP",
      "username": "0xtkyeo",
      "mindshare": 4.39,
      "projectId": 18,
      "duration": "7D",
      "updatedAt": 1763164792681,
      "follower_count": 3367,
      "smart_follower_count": 183,
      "insightfullness": null,
      "originality": null,
      "yaps_all": null
    },
    {
      "id": 74838,
      "name": "Leafswan",
      "rank": 8,
      "user_id": "-1",
      "topic_id": "DEFIAPP",
      "username": "leaf_swan",
      "mindshare": 3.72,
      "projectId": 18,
      "duration": "7D",
      "updatedAt": 1763164792681,
      "follower_count": 69479,
      "smart_follower_count": 1380,
      "insightfullness": null,
      "originality": null,
      "yaps_all": 566.94
    },
    {
      "id": 74839,
      "name": "medo | MemeMax⚡️",
      "rank": 9,
      "user_id": "-1",
      "topic_id": "DEFIAPP",
      "username": "medo_NFP",
      "mindshare": 3.62,
      "projectId": 18,
      "duration": "7D",
      "updatedAt": 1763164792681,
      "follower_count": 13342,
      "smart_follower_count": 259,
      "insightfullness": null,
      "originality": null,
      "yaps_all": null
    },
    {
      "id": 74840,
      "name": "DANIEL 🎩🔥",
      "rank": 10,
      "user_id": "-1",
      "topic_id": "DEFIAPP",
      "username": "daniarchibong_",
      "mindshare": 3.25,
      "projectId": 18,
      "duration": "7D",
      "updatedAt": 1763164792681,
      "follower_count": 2355,
      "smart_follower_count": 13,
      "insightfullness": null,
      "originality": null,
      "yaps_all": null
    },
    {
      "id": 74841,
      "name": "flarrs.edge🦭",
      "rank": 11,
      "user_id": "-1",
      "topic_id": "DEFIAPP",
      "username": "flarrs315",
      "mindshare": 2.19,
      "projectId": 18,
      "duration": "7D",
      "updatedAt": 1763164792681,
      "follower_count": 16029,
      "smart_follower_count": 311,
      "insightfullness": null,
      "originality": null,
      "yaps_all": 1043.17
    },
    {
      "id": 74842,
      "name": "IBCIG",
      "rank": 12,
      "user_id": "-1",
      "topic_id": "DEFIAPP",
      "username": "ibcig",
      "mindshare": 1.93,
      "projectId": 18,
      "duration": "7D",
      "updatedAt": 1763164792681,
      "follower_count": 535297,
      "smart_follower_count": 340,
      "insightfullness": null,
      "originality": null,
      "yaps_all": 265.56
    },
    {
      "id": 74843,
      "name": "Wraith🎩",
      "rank": 13,
      "user_id": "-1",
      "topic_id": "DEFIAPP",
      "username": "_CryptWraith",
      "mindshare": 1.88,
      "projectId": 18,
      "duration": "7D",
      "updatedAt": 1763164792681,
      "follower_count": 1221,
      "smart_follower_count": 12,
      "insightfullness": null,
      "originality": null,
      "yaps_all": null
    },
    {
      "id": 74844,
      "name": "Inferno",
      "rank": 14,
      "user_id": "-1",
      "topic_id": "DEFIAPP",
      "username": "infernoxbt",
      "mindshare": 1.51,
      "projectId": 18,
      "duration": "7D",
      "updatedAt": 1763164792681,
      "follower_count": 3192,
      "smart_follower_count": 36,
      "insightfullness": null,
      "originality": null,
      "yaps_all": null
    },
    {
      "id": 74845,
      "name": "Jimmywontgiveup(Ø,G)",
      "rank": 15,
      "user_id": "-1",
      "topic_id": "DEFIAPP",
      "username": "jimmywontgiveup",
      "mindshare": 1.24,
      "projectId": 18,
      "duration": "7D",
      "updatedAt": 1763164792681,
      "follower_count": 3002,
      "smart_follower_count": 29,
      "insightfullness": null,
      "originality": null,
      "yaps_all": 90.32
    },
    {
      "id": 74846,
      "name": "AJDominic (🐱,🐐)",
      "rank": 16,
      "user_id": "-1",
      "topic_id": "DEFIAPP",
      "username": "A_J_Dominic",
      "mindshare": 1.2,
      "projectId": 18,
      "duration": "7D",
      "updatedAt": 1763164792681,
      "follower_count": 6535,
      "smart_follower_count": 45,
      "insightfullness": null,
      "originality": null,
      "yaps_all": null
    },
    {
      "id": 74847,
      "name": "Khanz Fodé",
      "rank": 17,
      "user_id": "-1",
      "topic_id": "DEFIAPP",
      "username": "KhanzFacts",
      "mindshare": 1.12,
      "projectId": 18,
      "duration": "7D",
      "updatedAt": 1763164792681,
      "follower_count": 2747,
      "smart_follower_count": 44,
      "insightfullness": null,
      "originality": null,
      "yaps_all": 48.9
    },
    {
      "id": 74848,
      "name": "Shinkiro",
      "rank": 18,
      "user_id": "-1",
      "topic_id": "DEFIAPP",
      "username": "ShinKiro14",
      "mindshare": 1.11,
      "projectId": 18,
      "duration": "7D",
      "updatedAt": 1763164792681,
      "follower_count": 1533,
      "smart_follower_count": 78,
      "insightfullness": null,
      "originality": null,
      "yaps_all": null
    },
    {
      "id": 74849,
      "name": "Zoop",
      "rank": 19,
      "user_id": "-1",
      "topic_id": "DEFIAPP",
      "username": "zoop_t",
      "mindshare": 1.05,
      "projectId": 18,
      "duration": "7D",
      "updatedAt": 1763164792681,
      "follower_count": 2083,
      "smart_follower_count": 97,
      "insightfullness": null,
      "originality": null,
      "yaps_all": null
    },
    {
      "id": 74850,
      "name": "buttercup",
      "rank": 20,
      "user_id": "-1",
      "topic_id": "DEFIAPP",
      "username": "butteryconcept",
      "mindshare": 0.93,
      "projectId": 18,
      "duration": "7D",
      "updatedAt": 1763164792681,
      "follower_count": 952,
      "smart_follower_count": 5,
      "insightfullness": null,
      "originality": null,
      "yaps_all": null
    },
    {
      "id": 74851,
      "name": "Prepz 🎩",
      "rank": 21,
      "user_id": "-1",
      "topic_id": "DEFIAPP",
      "username": "lordprepz",
      "mindshare": 0.93,
      "projectId": 18,
      "duration": "7D",
      "updatedAt": 1763164792681,
      "follower_count": 2460,
      "smart_follower_count": 23,
      "insightfullness": null,
      "originality": null,
      "yaps_all": null
    },
    {
      "id": 74852,
      "name": "Crypp",
      "rank": 22,
      "user_id": "-1",
      "topic_id": "DEFIAPP",
      "username": "cryppinfluence",
      "mindshare": 0.88,
      "projectId": 18,
      "duration": "7D",
      "updatedAt": 1763164792681,
      "follower_count": 48866,
      "smart_follower_count": 225,
      "insightfullness": null,
      "originality": null,
      "yaps_all": null
    },
    {
      "id": 74853,
      "name": "𝕊𝕄Ø𝕂𝔼ℝ",
      "rank": 23,
      "user_id": "-1",
      "topic_id": "DEFIAPP",
      "username": "WwRabitto",
      "mindshare": 0.67,
      "projectId": 18,
      "duration": "7D",
      "updatedAt": 1763164792681,
      "follower_count": 1337,
      "smart_follower_count": 3,
      "insightfullness": null,
      "originality": null,
      "yaps_all": null
    },
    {
      "id": 74854,
      "name": "𝑺𝑻𝑬𝑨𝑳𝑻𝑯🎩",
      "rank": 24,
      "user_id": "-1",
      "topic_id": "DEFIAPP",
      "username": "jesugbolahanmi",
      "mindshare": 0.67,
      "projectId": 18,
      "duration": "7D",
      "updatedAt": 1763164792681,
      "follower_count": 1850,
      "smart_follower_count": 15,
      "insightfullness": null,
      "originality": null,
      "yaps_all": null
    },
    {
      "id": 74855,
      "name": "EDEX",
      "rank": 25,
      "user_id": "-1",
      "topic_id": "DEFIAPP",
      "username": "EDEXEmperor",
      "mindshare": 0.64,
      "projectId": 18,
      "duration": "7D",
      "updatedAt": 1763164792681,
      "follower_count": 532,
      "smart_follower_count": 3,
      "insightfullness": null,
      "originality": null,
      "yaps_all": null
    },
    {
      "id": 74856,
      "name": "코루🍊 .edge🦭",
      "rank": 26,
      "user_id": "-1",
      "topic_id": "DEFIAPP",
      "username": "colu_farmer",
      "mindshare": 0.61,
      "projectId": 18,
      "duration": "7D",
      "updatedAt": 1763164792681,
      "follower_count": 35147,
      "smart_follower_count": 300,
      "insightfullness": null,
      "originality": null,
      "yaps_all": 989.37
    },
    {
      "id": 74857,
      "name": "ÍMØÑ🐉",
      "rank": 27,
      "user_id": "-1",
      "topic_id": "DEFIAPP",
      "username": "IMON_2014",
      "mindshare": 0.52,
      "projectId": 18,
      "duration": "7D",
      "updatedAt": 1763164792681,
      "follower_count": 1339,
      "smart_follower_count": 2,
      "insightfullness": null,
      "originality": null,
      "yaps_all": null
    },
    {
      "id": 74858,
      "name": "Finish 🏁",
      "rank": 28,
      "user_id": "-1",
      "topic_id": "DEFIAPP",
      "username": "0xFinish",
      "mindshare": 0.34,
      "projectId": 18,
      "duration": "7D",
      "updatedAt": 1763164792681,
      "follower_count": 143536,
      "smart_follower_count": 857,
      "insightfullness": null,
      "originality": null,
      "yaps_all": null
    },
    {
      "id": 74859,
      "name": "some.edge🦭/MemeMax⚡️/∞KIN/🌊RIVER/(❖,❖)",
      "rank": 29,
      "user_id": "-1",
      "topic_id": "DEFIAPP",
      "username": "some4064",
      "mindshare": 0.32,
      "projectId": 18,
      "duration": "7D",
      "updatedAt": 1763164792681,
      "follower_count": 2542,
      "smart_follower_count": 57,
      "insightfullness": null,
      "originality": null,
      "yaps_all": null
    },
    {
      "id": 37285626,
      "name": "🎀Barbie🎀",
      "rank": 30,
      "user_id": "-1",
      "topic_id": "DEFIAPP",
      "username": "barbieverse_",
      "mindshare": 0.32,
      "projectId": 18,
      "duration": "7D",
      "updatedAt": 1763164792681,
      "follower_count": 4374,
      "smart_follower_count": 2,
      "insightfullness": null,
      "originality": null,
      "yaps_all": null
    },
    {
      "id": 37375925,
      "name": "𖤍Farmarcis🐦‍🔥☄️🌶️",
      "rank": 31,
      "user_id": "-1",
      "topic_id": "DEFIAPP",
      "username": "farmarcis",
      "mindshare": 0.24,
      "projectId": 18,
      "duration": "7D",
      "updatedAt": 1763164792681,
      "follower_count": 3356,
      "smart_follower_count": 12,
      "insightfullness": null,
      "originality": null,
      "yaps_all": null
    },
    {
      "id": 37698138,
      "name": "Naya",
      "rank": 32,
      "user_id": "-1",
      "topic_id": "DEFIAPP",
      "username": "Naya6039",
      "mindshare": 0.19,
      "projectId": 18,
      "duration": "7D",
      "updatedAt": 1763164792681,
      "follower_count": 1608,
      "smart_follower_count": 36,
      "insightfullness": null,
      "originality": null,
      "yaps_all": null
    },
    {
      "id": 38250189,
      "name": "CryptoMaid加密女仆お嬢様 Ⓜ️Ⓜ️T",
      "rank": 33,
      "user_id": "-1",
      "topic_id": "DEFIAPP",
      "username": "maid_crypto",
      "mindshare": 0.12,
      "projectId": 18,
      "duration": "7D",
      "updatedAt": 1763164792681,
      "follower_count": 136835,
      "smart_follower_count": 567,
      "insightfullness": null,
      "originality": null,
      "yaps_all": 2772.07
    },
    {
      "id": 38388589,
      "name": "Superfly🦅",
      "rank": 34,
      "user_id": "-1",
      "topic_id": "DEFIAPP",
      "username": "killsh0tx",
      "mindshare": 0.06,
      "projectId": 18,
      "duration": "7D",
      "updatedAt": 1763164792681,
      "follower_count": 1044,
      "smart_follower_count": 18,
      "insightfullness": null,
      "originality": null,
      "yaps_all": 25.79
    },
    {
      "id": 38939114,
      "name": "Peno 🎩",
      "rank": 35,
      "user_id": "-1",
      "topic_id": "DEFIAPP",
      "username": "_philipeno",
      "mindshare": 0.04,
      "projectId": 18,
      "duration": "7D",
      "updatedAt": 1763164792681,
      "follower_count": 556,
      "smart_follower_count": 5,
      "insightfullness": null,
      "originality": null,
      "yaps_all": null
    },
    {
      "id": 41515425,
      "name": "W.edge🦭MemeMax⚡️",
      "rank": 36,
      "user_id": "-1",
      "topic_id": "DEFIAPP",
      "username": "Future24146",
      "mindshare": 0.01,
      "projectId": 18,
      "duration": "7D",
      "updatedAt": 1763164792681,
      "follower_count": 1296,
      "smart_follower_count": 15,
      "insightfullness": null,
      "originality": null,
      "yaps_all": null
    }
  ]
}