{
  "data": [
    {
      "id": 51351481,
      "name": "SteveDKrypt.sui ❖,❖",
      "rank": 1,
      "user_id": "-1",
      "topic_id": "INFERENCELABS",
      "username": "Busaristephen",
      "mindshare": 5.33,
      "projectId": 341,
      "duration": "7D",
      "updatedAt": 1765065523721,
      "follower_count": 3106,
      "smart_follower_count": 7,
      "insightfullness": null,
      "originality": null
    },
    {
      "id": 51351482,
      "name": "Steve",
      "rank": 2,
      "user_id": "-1",
      "topic_id": "INFERENCELABS",
      "username": "Roolaand001",
      "mindshare": 2.81,
      "projectId": 341,
      "duration": "7D",
      "updatedAt": 1765065523721,
      "follower_count": 1412,
      "smart_follower_count": 3,
      "insightfullness": null,
      "originality": null
    },
    {
      "id": 51351483,
      "name": "fold",
      "rank": 3,
      "user_id": "-1",
      "topic_id": "INFERENCELABS",
      "username": "foldmiracle",
      "mindshare": 1.96,
      "projectId": 341,
      "duration": "7D",
      "updatedAt": 1765065523721,
      "follower_count": 915,
      "smart_follower_count": 3,
      "insightfullness": null,
      "originality": null
    },
    {
      "id": 51351484,
      "name": "NamHai_F4 .edge🦭𝔽rAI 🌊RIVER",
      "rank": 4,
      "user_id": "-1",
      "topic_id": "INFERENCELABS",
      "username": "NamHai_Cao",
      "mindshare": 1.92,
      "projectId": 341,
      "duration": "7D",
      "updatedAt": 1765065523721,
      "follower_count": 3690,
      "smart_follower_count": 2,
      "insightfullness": null,
      "originality": null
    },
    {
      "id": 51351485,
      "name": "Pars ♢ / ₿",
      "rank": 5,
      "user_id": "-1",
      "topic_id": "INFERENCELABS",
      "username": "Alphapars",
      "mindshare": 1.91,
      "projectId": 341,
      "duration": "7D",
      "updatedAt": 1765065523721,
      "follower_count": 14611,
      "smart_follower_count": 42,
      "insightfullness": null,
      "originality": null
    },
    {
      "id": 51351486,
      "name": "Vav Crypto 🌊",
      "rank": 6,
      "user_id": "-1",
      "topic_id": "INFERENCELABS",
      "username": "VaveylaCrypto",
      "mindshare": 1.85,
      "projectId": 341,
      "duration": "7D",
      "updatedAt": 1765065523721,
      "follower_count": 17236,
      "smart_follower_count": 160,
      "insightfullness": null,
      "originality": null
    },
    {
      "id": 51351487,
      "name": "Ron C",
      "rank": 7,
      "user_id": "-1",
      "topic_id": "INFERENCELABS",
      "username": "sudo_ron",
      "mindshare": 1.63,
      "projectId": 341,
      "duration": "7D",
      "updatedAt": 1765065523721,
      "follower_count": 6161,
      "smart_follower_count": 64,
      "insightfullness": null,
      "originality": null
    },
    {
      "id": 51351488,
      "name": "Tapan.Eth🌊",
      "rank": 8,
      "user_id": "-1",
      "topic_id": "INFERENCELABS",
      "username": "TapanDeFi",
      "mindshare": 1.59,
      "projectId": 341,
      "duration": "7D",
      "updatedAt": 1765065523721,
      "follower_count": 3545,
      "smart_follower_count": 5,
      "insightfullness": null,
      "originality": null
    },
    {
      "id": 51351489,
      "name": "Tim Haldorsson",
      "rank": 9,
      "user_id": "-1",
      "topic_id": "INFERENCELABS",
      "username": "TimHaldorsson",
      "mindshare": 1.57,
      "projectId": 341,
      "duration": "7D",
      "updatedAt": 1765065523721,
      "follower_count": 31575,
      "smart_follower_count": 757,
      "insightfullness": null,
      "originality": null
    },
    {
      "id": 51351490,
      "name": "Domen T.",
      "rank": 10,
      "user_id": "-1",
      "topic_id": "INFERENCELABS",
      "username": "DomOnChain",
      "mindshare": 1.38,
      "projectId": 341,
      "duration": "7D",
      "updatedAt": 1765065523721,
      "follower_count": 48027,
      "smart_follower_count": 123,
      "insightfullness": null,
      "originality": null
    },
    {
      "id": 51351491,
      "name": "lomo",
      "rank": 11,
      "user_id": "-1",
      "topic_id": "INFERENCELABS",
      "username": "lomoint",
      "mindshare": 1.32,
      "projectId": 341,
      "duration": "7D",
      "updatedAt": 1765065523721,
      "follower_count": 2030,
      "smart_follower_count": 40,
      "insightfullness": null,
      "originality": null
    },
    {
      "id": 51351492,
      "name": "TUKI (툭이) ∞ KIN | MemeMax ⚡️| .edge 🦭| 싸이식",
      "rank": 12,
      "user_id": "-1",
      "topic_id": "INFERENCELABS",
      "username": "Ty_Tuki0609",
      "mindshare": 1.24,
      "projectId": 341,
      "duration": "7D",
      "updatedAt": 1765065523721,
      "follower_count": 3107,
      "smart_follower_count": 55,
      "insightfullness": null,
      "originality": null
    },
    {
      "id": 51351493,
      "name": "Holly",
      "rank": 13,
      "user_id": "-1",
      "topic_id": "INFERENCELABS",
      "username": "holly_web3",
      "mindshare": 1.11,
      "projectId": 341,
      "duration": "7D",
      "updatedAt": 1765065523721,
      "follower_count": 52744,
      "smart_follower_count": 305,
      "insightfullness": null,
      "originality": null
    },
    {
      "id": 51351494,
      "name": "ALTF4",
      "rank": 14,
      "user_id": "-1",
      "topic_id": "INFERENCELABS",
      "username": "0xALTF4",
      "mindshare": 1.09,
      "projectId": 341,
      "duration": "7D",
      "updatedAt": 1765065523721,
      "follower_count": 70823,
      "smart_follower_count": 569,
      "insightfullness": null,
      "originality": null
    },
    {
      "id": 51351495,
      "name": "𝟘𝕩𝕊𝕖𝕤𝕤𝕙𝕠🌙",
      "rank": 15,
      "user_id": "-1",
      "topic_id": "INFERENCELABS",
      "username": "0xSessho",
      "mindshare": 1.08,
      "projectId": 341,
      "duration": "7D",
      "updatedAt": 1765065523721,
      "follower_count": 2439,
      "smart_follower_count": 5,
      "insightfullness": null,
      "originality": null
    },
    {
      "id": 51351496,
      "name": "드라 | DRA",
      "rank": 16,
      "user_id": "-1",
      "topic_id": "INFERENCELABS",
      "username": "baggyudong78463",
      "mindshare": 1.07,
      "projectId": 341,
      "duration": "7D",
      "updatedAt": 1765065523721,
      "follower_count": 2192,
      "smart_follower_count": 133,
      "insightfullness": null,
      "originality": null
    },
    {
      "id": 51351497,
      "name": "MICHOKINGS - NOYA",
      "rank": 17,
      "user_id": "-1",
      "topic_id": "INFERENCELABS",
      "username": "MichOkings",
      "mindshare": 1.01,
      "projectId": 341,
      "duration": "7D",
      "updatedAt": 1765065523721,
      "follower_count": 2860,
      "smart_follower_count": 13,
      "insightfullness": null,
      "originality": null
    },
    {
      "id": 51351498,
      "name": "Brano",
      "rank": 18,
      "user_id": "-1",
      "topic_id": "INFERENCELABS",
      "username": "branovic1i",
      "mindshare": 0.98,
      "projectId": 341,
      "duration": "7D",
      "updatedAt": 1765065523721,
      "follower_count": 3232,
      "smart_follower_count": 25,
      "insightfullness": null,
      "originality": null
    },
    {
      "id": 51351499,
      "name": "Mono",
      "rank": 19,
      "user_id": "-1",
      "topic_id": "INFERENCELABS",
      "username": "0xxMono",
      "mindshare": 0.93,
      "projectId": 341,
      "duration": "7D",
      "updatedAt": 1765065523721,
      "follower_count": 1251,
      "smart_follower_count": 9,
      "insightfullness": null,
      "originality": null
    },
    {
      "id": 51351500,
      "name": "Khánh Nheii Ⓜ️Ⓜ️T",
      "rank": 20,
      "user_id": "-1",
      "topic_id": "INFERENCELABS",
      "username": "HuNghaL6",
      "mindshare": 0.91,
      "projectId": 341,
      "duration": "7D",
      "updatedAt": 1765065523721,
      "follower_count": 2507,
      "smart_follower_count": 6,
      "insightfullness": null,
      "originality": null
    },
    {
      "id": 51351501,
      "name": "heunggoo MemeMax ⚡️ ∞ KIN",
      "rank": 21,
      "user_id": "-1",
      "topic_id": "INFERENCELABS",
      "username": "heungmangoo",
      "mindshare": 0.86,
      "projectId": 341,
      "duration": "7D",
      "updatedAt": 1765065523721,
      "follower_count": 8282,
      "smart_follower_count": 146,
      "insightfullness": null,
      "originality": null
    },
    {
      "id": 51351502,
      "name": "우즈마키 얍루토",
      "rank": 22,
      "user_id": "-1",
      "topic_id": "INFERENCELABS",
      "username": "naruto_yapper",
      "mindshare": 0.85,
      "projectId": 341,
      "duration": "7D",
      "updatedAt": 1765065523721,
      "follower_count": 363,
      "smart_follower_count": 21,
      "insightfullness": null,
      "originality": null
    },
    {
      "id": 51351503,
      "name": "0xFerdi.eth",
      "rank": 23,
      "user_id": "-1",
      "topic_id": "INFERENCELABS",
      "username": "mr_ferdiansah",
      "mindshare": 0.78,
      "projectId": 341,
      "duration": "7D",
      "updatedAt": 1765065523721,
      "follower_count": 4454,
      "smart_follower_count": 30,
      "insightfullness": null,
      "originality": null
    },
    {
      "id": 51351504,
      "name": "0xlolz(✧ᴗ✧)",
      "rank": 24,
      "user_id": "-1",
      "topic_id": "INFERENCELABS",
      "username": "Oxlolz",
      "mindshare": 0.76,
      "projectId": 341,
      "duration": "7D",
      "updatedAt": 1765065523721,
      "follower_count": 2473,
      "smart_follower_count": 54,
      "insightfullness": null,
      "originality": null
    },
    {
      "id": 51351505,
      "name": "𝗖𝗿𝘆𝗽𝘁𝗼𝗣𝗮𝗻𝗱𝗮",
      "rank": 25,
      "user_id": "-1",
      "topic_id": "INFERENCELABS",
      "username": "MrCryptoPandaa",
      "mindshare": 0.76,
      "projectId": 341,
      "duration": "7D",
      "updatedAt": 1765065523721,
      "follower_count": 1580,
      "smart_follower_count": 23,
      "insightfullness": null,
      "originality": null
    },
    {
      "id": 51351506,
      "name": "SHOAIB UDDIN | 𝔽rAI",
      "rank": 26,
      "user_id": "-1",
      "topic_id": "INFERENCELABS",
      "username": "shoaib7929276",
      "mindshare": 0.75,
      "projectId": 341,
      "duration": "7D",
      "updatedAt": 1765065523721,
      "follower_count": 7375,
      "smart_follower_count": 20,
      "insightfullness": null,
      "originality": null
    },
    {
      "id": 51351507,
      "name": "Loper.MemeMax⚡️.싸이식🌊RIVER",
      "rank": 27,
      "user_id": "-1",
      "topic_id": "INFERENCELABS",
      "username": "leveb_devel",
      "mindshare": 0.74,
      "projectId": 341,
      "duration": "7D",
      "updatedAt": 1765065523721,
      "follower_count": 1627,
      "smart_follower_count": 29,
      "insightfullness": null,
      "originality": null
    },
    {
      "id": 51351508,
      "name": "Usopp",
      "rank": 28,
      "user_id": "-1",
      "topic_id": "INFERENCELABS",
      "username": "CryptoUsopp",
      "mindshare": 0.74,
      "projectId": 341,
      "duration": "7D",
      "updatedAt": 1765065523721,
      "follower_count": 45803,
      "smart_follower_count": 409,
      "insightfullness": null,
      "originality": null
    },
    {
      "id": 51351509,
      "name": "쥔장 MemeMax⚡️",
      "rank": 29,
      "user_id": "-1",
      "topic_id": "INFERENCELABS",
      "username": "beingRich2000",
      "mindshare": 0.73,
      "projectId": 341,
      "duration": "7D",
      "updatedAt": 1765065523721,
      "follower_count": 12888,
      "smart_follower_count": 210,
      "insightfullness": null,
      "originality": null
    },
    {
      "id": 51351510,
      "name": "dibo.MemeMax⚡️",
      "rank": 30,
      "user_id": "-1",
      "topic_id": "INFERENCELABS",
      "username": "Hoon11221",
      "mindshare": 0.72,
      "projectId": 341,
      "duration": "7D",
      "updatedAt": 1765065523721,
      "follower_count": 2456,
      "smart_follower_count": 85,
      "insightfullness": null,
      "originality": null
    },
    {
      "id": 51351511,
      "name": "sarang MemeMax⚡️극한찐따단",
      "rank": 31,
      "user_id": "-1",
      "topic_id": "INFERENCELABS",
      "username": "sarang3372",
      "mindshare": 0.66,
      "projectId": 341,
      "duration": "7D",
      "updatedAt": 1765065523721,
      "follower_count": 2316,
      "smart_follower_count": 42,
      "insightfullness": null,
      "originality": null
    },
    {
      "id": 51351512,
      "name": "얍바이브 MemeMax⚡️∞ KIN",
      "rank": 32,
      "user_id": "-1",
      "topic_id": "INFERENCELABS",
      "username": "YapVibe",
      "mindshare": 0.66,
      "projectId": 341,
      "duration": "7D",
      "updatedAt": 1765065523721,
      "follower_count": 3011,
      "smart_follower_count": 48,
      "insightfullness": null,
      "originality": null
    },
    {
      "id": 51351513,
      "name": "alfath",
      "rank": 33,
      "user_id": "-1",
      "topic_id": "INFERENCELABS",
      "username": "alfathjiee",
      "mindshare": 0.64,
      "projectId": 341,
      "duration": "7D",
      "updatedAt": 1765065523721,
      "follower_count": 4169,
      "smart_follower_count": 14,
      "insightfullness": null,
      "originality": null
    },
    {
      "id": 51351514,
      "name": "olafimihan$MGT",
      "rank": 34,
      "user_id": "-1",
      "topic_id": "INFERENCELABS",
      "username": "olafimihan2002",
      "mindshare": 0.63,
      "projectId": 341,
      "duration": "7D",
      "updatedAt": 1765065523721,
      "follower_count": 3171,
      "smart_follower_count": 2,
      "insightfullness": null,
      "originality": null
    },
    {
      "id": 51351515,
      "name": "김분유 🍼 .edge🦭",
      "rank": 35,
      "user_id": "-1",
      "topic_id": "INFERENCELABS",
      "username": "kimbunyu",
      "mindshare": 0.62,
      "projectId": 341,
      "duration": "7D",
      "updatedAt": 1765065523721,
      "follower_count": 3491,
      "smart_follower_count": 91,
      "insightfullness": null,
      "originality": null
    },
    {
      "id": 51351516,
      "name": "skysky",
      "rank": 36,
      "user_id": "-1",
      "topic_id": "INFERENCELABS",
      "username": "ohskying",
      "mindshare": 0.61,
      "projectId": 341,
      "duration": "7D",
      "updatedAt": 1765065523721,
      "follower_count": 1871,
      "smart_follower_count": 28,
      "insightfullness": null,
      "originality": null
    },
    {
      "id": 51351517,
      "name": "Kundo.base.eth MemeMax⚡️",
      "rank": 37,
      "user_id": "-1",
      "topic_id": "INFERENCELABS",
      "username": "kkangdh8294",
      "mindshare": 0.58,
      "projectId": 341,
      "duration": "7D",
      "updatedAt": 1765065523721,
      "follower_count": 1415,
      "smart_follower_count": 29,
      "insightfullness": null,
      "originality": null
    },
    {
      "id": 51351518,
      "name": "GODGRACEE",
      "rank": 38,
      "user_id": "-1",
      "topic_id": "INFERENCELABS",
      "username": "investormikeo2",
      "mindshare": 0.55,
      "projectId": 341,
      "duration": "7D",
      "updatedAt": 1765065523721,
      "follower_count": 3141,
      "smart_follower_count": 10,
      "insightfullness": null,
      "originality": null
    },
    {
      "id": 51351519,
      "name": "haeppiㅣMemeMax⚡️",
      "rank": 39,
      "user_id": "-1",
      "topic_id": "INFERENCELABS",
      "username": "hae_pping",
      "mindshare": 0.54,
      "projectId": 341,
      "duration": "7D",
      "updatedAt": 1765065523721,
      "follower_count": 2039,
      "smart_follower_count": 44,
      "insightfullness": null,
      "originality": null
    },
    {
      "id": 51351520,
      "name": "여누두ッ🌊RIVER|싸이식",
      "rank": 40,
      "user_id": "-1",
      "topic_id": "INFERENCELABS",
      "username": "yeonudooo",
      "mindshare": 0.52,
      "projectId": 341,
      "duration": "7D",
      "updatedAt": 1765065523721,
      "follower_count": 2961,
      "smart_follower_count": 59,
      "insightfullness": null,
      "originality": null
    },
    {
      "id": 51351521,
      "name": "ToBornSun｜edge 🦭 MemeMax ⚡️",
      "rank": 41,
      "user_id": "-1",
      "topic_id": "INFERENCELABS",
      "username": "ToBornSun_",
      "mindshare": 0.52,
      "projectId": 341,
      "duration": "7D",
      "updatedAt": 1765065523721,
      "follower_count": 1570,
      "smart_follower_count": 47,
      "insightfullness": null,
      "originality": null
    },
    {
      "id": 51351522,
      "name": "Golf",
      "rank": 42,
      "user_id": "-1",
      "topic_id": "INFERENCELABS",
      "username": "Golf_268",
      "mindshare": 0.52,
      "projectId": 341,
      "duration": "7D",
      "updatedAt": 1765065523721,
      "follower_count": 3305,
      "smart_follower_count": 24,
      "insightfullness": null,
      "originality": null
    },
    {
      "id": 51351523,
      "name": "Niso",
      "rank": 43,
      "user_id": "-1",
      "topic_id": "INFERENCELABS",
      "username": "Just_Niso",
      "mindshare": 0.5,
      "projectId": 341,
      "duration": "7D",
      "updatedAt": 1765065523721,
      "follower_count": 2810,
      "smart_follower_count": 4,
      "insightfullness": null,
      "originality": null
    },
    {
      "id": 51351524,
      "name": "等我一期双色球",
      "rank": 44,
      "user_id": "-1",
      "topic_id": "INFERENCELABS",
      "username": "LiuNengBoy",
      "mindshare": 0.49,
      "projectId": 341,
      "duration": "7D",
      "updatedAt": 1765065523721,
      "follower_count": 1814,
      "smart_follower_count": 5,
      "insightfullness": null,
      "originality": null
    },
    {
      "id": 51351525,
      "name": "Denka Raya TAP🚰 $AVRK",
      "rank": 45,
      "user_id": "-1",
      "topic_id": "INFERENCELABS",
      "username": "DenkaRaya",
      "mindshare": 0.49,
      "projectId": 341,
      "duration": "7D",
      "updatedAt": 1765065523721,
      "follower_count": 58,
      "smart_follower_count": 1,
      "insightfullness": null,
      "originality": null
    },
    {
      "id": 51351526,
      "name": "Ayoo",
      "rank": 46,
      "user_id": "-1",
      "topic_id": "INFERENCELABS",
      "username": "AyooXCT",
      "mindshare": 0.49,
      "projectId": 341,
      "duration": "7D",
      "updatedAt": 1765065523721,
      "follower_count": 1715,
      "smart_follower_count": 3,
      "insightfullness": null,
      "originality": null
    },
    {
      "id": 51351527,
      "name": "Solo",
      "rank": 47,
      "user_id": "-1",
      "topic_id": "INFERENCELABS",
      "username": "sololeveling006",
      "mindshare": 0.49,
      "projectId": 341,
      "duration": "7D",
      "updatedAt": 1765065523721,
      "follower_count": 4268,
      "smart_follower_count": 5,
      "insightfullness": null,
      "originality": null
    },
    {
      "id": 51351528,
      "name": "boy_ov 🇳🇬",
      "rank": 48,
      "user_id": "-1",
      "topic_id": "INFERENCELABS",
      "username": "ov_crypt",
      "mindshare": 0.47,
      "projectId": 341,
      "duration": "7D",
      "updatedAt": 1765065523721,
      "follower_count": 2128,
      "smart_follower_count": 2,
      "insightfullness": null,
      "originality": null
    },
    {
      "id": 51351529,
      "name": "Gyo",
      "rank": 49,
      "user_id": "-1",
      "topic_id": "INFERENCELABS",
      "username": "Gyokeres_eth",
      "mindshare": 0.46,
      "projectId": 341,
      "duration": "7D",
      "updatedAt": 1765065523721,
      "follower_count": 12944,
      "smart_follower_count": 150,
      "insightfullness": null,
      "originality": null
    },
    {
      "id": 51351530,
      "name": "냥얍. 싸이식 | MemeMax ⚡️",
      "rank": 50,
      "user_id": "-1",
      "topic_id": "INFERENCELABS",
      "username": "nyangyap",
      "mindshare": 0.45,
      "projectId": 341,
      "duration": "7D",
      "updatedAt": 1765065523721,
      "follower_count": 2956,
      "smart_follower_count": 40,
      "insightfullness": null,
      "originality": null
    },
    {
      "id": 51351531,
      "name": "MadaraOnChain🫎",
      "rank": 51,
      "user_id": "-1",
      "topic_id": "INFERENCELABS",
      "username": "Tywice_O",
      "mindshare": 0.45,
      "projectId": 341,
      "duration": "7D",
      "updatedAt": 1765065523721,
      "follower_count": 1795,
      "smart_follower_count": 3,
      "insightfullness": null,
      "originality": null
    },
    {
      "id": 51351532,
      "name": "Muco",
      "rank": 52,
      "user_id": "-1",
      "topic_id": "INFERENCELABS",
      "username": "Mucttc",
      "mindshare": 0.44,
      "projectId": 341,
      "duration": "7D",
      "updatedAt": 1765065523721,
      "follower_count": 2662,
      "smart_follower_count": 45,
      "insightfullness": null,
      "originality": null
    },
    {
      "id": 51351533,
      "name": "TraviSKrypto🥷🐝",
      "rank": 53,
      "user_id": "-1",
      "topic_id": "INFERENCELABS",
      "username": "__traviSKrypto",
      "mindshare": 0.44,
      "projectId": 341,
      "duration": "7D",
      "updatedAt": 1765065523721,
      "follower_count": 3133,
      "smart_follower_count": 43,
      "insightfullness": null,
      "originality": null
    },
    {
      "id": 51351534,
      "name": "Casper🍊,💊",
      "rank": 54,
      "user_id": "-1",
      "topic_id": "INFERENCELABS",
      "username": "CasperDey4U",
      "mindshare": 0.43,
      "projectId": 341,
      "duration": "7D",
      "updatedAt": 1765065523721,
      "follower_count": 1224,
      "smart_follower_count": 8,
      "insightfullness": null,
      "originality": null
    },
    {
      "id": 51351535,
      "name": "Øxtoby🦣",
      "rank": 55,
      "user_id": "-1",
      "topic_id": "INFERENCELABS",
      "username": "Tobiloba_x1",
      "mindshare": 0.42,
      "projectId": 341,
      "duration": "7D",
      "updatedAt": 1765065523721,
      "follower_count": 1454,
      "smart_follower_count": 10,
      "insightfullness": null,
      "originality": null
    },
    {
      "id": 51351536,
      "name": "Chinmay",
      "rank": 56,
      "user_id": "-1",
      "topic_id": "INFERENCELABS",
      "username": "time_and_fate",
      "mindshare": 0.42,
      "projectId": 341,
      "duration": "7D",
      "updatedAt": 1765065523721,
      "follower_count": 2480,
      "smart_follower_count": 27,
      "insightfullness": null,
      "originality": null
    },
    {
      "id": 51351537,
      "name": "🌱GridMinds 🌊",
      "rank": 57,
      "user_id": "-1",
      "topic_id": "INFERENCELABS",
      "username": "gridminds",
      "mindshare": 0.42,
      "projectId": 341,
      "duration": "7D",
      "updatedAt": 1765065523721,
      "follower_count": 3249,
      "smart_follower_count": 5,
      "insightfullness": null,
      "originality": null
    },
    {
      "id": 51351538,
      "name": "Experiment",
      "rank": 58,
      "user_id": "-1",
      "topic_id": "INFERENCELABS",
      "username": "Isuleims",
      "mindshare": 0.42,
      "projectId": 341,
      "duration": "7D",
      "updatedAt": 1765065523721,
      "follower_count": 1545,
      "smart_follower_count": 3,
      "insightfullness": null,
      "originality": null
    },
    {
      "id": 51351539,
      "name": "쮸 | jjjjjuuuuu.edge🦭(❖,❖) MemeMax⚡️",
      "rank": 59,
      "user_id": "-1",
      "topic_id": "INFERENCELABS",
      "username": "koup4028",
      "mindshare": 0.41,
      "projectId": 341,
      "duration": "7D",
      "updatedAt": 1765065523721,
      "follower_count": 2866,
      "smart_follower_count": 80,
      "insightfullness": null,
      "originality": null
    },
    {
      "id": 51351540,
      "name": "TianaDang | Morph | Ⓜ️Ⓜ️T | 🌊RIVER | .edge🦭",
      "rank": 60,
      "user_id": "-1",
      "topic_id": "INFERENCELABS",
      "username": "Tianadang0910",
      "mindshare": 0.4,
      "projectId": 341,
      "duration": "7D",
      "updatedAt": 1765065523721,
      "follower_count": 2332,
      "smart_follower_count": 10,
      "insightfullness": null,
      "originality": null
    },
    {
      "id": 51351541,
      "name": "Kennedy",
      "rank": 61,
      "user_id": "-1",
      "topic_id": "INFERENCELABS",
      "username": "Lord_Ken10",
      "mindshare": 0.39,
      "projectId": 341,
      "duration": "7D",
      "updatedAt": 1765065523721,
      "follower_count": 129,
      "smart_follower_count": 0,
      "insightfullness": null,
      "originality": null
    },
    {
      "id": 51351542,
      "name": "贰房东Bird🕊️",
      "rank": 62,
      "user_id": "-1",
      "topic_id": "INFERENCELABS",
      "username": "xyzlafx",
      "mindshare": 0.39,
      "projectId": 341,
      "duration": "7D",
      "updatedAt": 1765065523721,
      "follower_count": 5619,
      "smart_follower_count": 22,
      "insightfullness": null,
      "originality": null
    },
    {
      "id": 51351543,
      "name": "awe.",
      "rank": 63,
      "user_id": "-1",
      "topic_id": "INFERENCELABS",
      "username": "Gabii_awee",
      "mindshare": 0.39,
      "projectId": 341,
      "duration": "7D",
      "updatedAt": 1765065523721,
      "follower_count": 3768,
      "smart_follower_count": 19,
      "insightfullness": null,
      "originality": null
    },
    {
      "id": 51351544,
      "name": "Cipher Scrolls",
      "rank": 64,
      "user_id": "-1",
      "topic_id": "INFERENCELABS",
      "username": "siliveru_v30261",
      "mindshare": 0.39,
      "projectId": 341,
      "duration": "7D",
      "updatedAt": 1765065523721,
      "follower_count": 2257,
      "smart_follower_count": 12,
      "insightfullness": null,
      "originality": null
    },
    {
      "id": 51351545,
      "name": "Phemite ꧁IP꧂ CLONE 🦙🔥",
      "rank": 65,
      "user_id": "-1",
      "topic_id": "INFERENCELABS",
      "username": "LordphemitShawn",
      "mindshare": 0.39,
      "projectId": 341,
      "duration": "7D",
      "updatedAt": 1765065523721,
      "follower_count": 77,
      "smart_follower_count": 1,
      "insightfullness": null,
      "originality": null
    },
    {
      "id": 51351546,
      "name": "Emagine",
      "rank": 66,
      "user_id": "-1",
      "topic_id": "INFERENCELABS",
      "username": "King_Emagine",
      "mindshare": 0.38,
      "projectId": 341,
      "duration": "7D",
      "updatedAt": 1765065523721,
      "follower_count": 893,
      "smart_follower_count": 7,
      "insightfullness": null,
      "originality": null
    },
    {
      "id": 51351547,
      "name": "Rey",
      "rank": 67,
      "user_id": "-1",
      "topic_id": "INFERENCELABS",
      "username": "reyGszn",
      "mindshare": 0.38,
      "projectId": 341,
      "duration": "7D",
      "updatedAt": 1765065523721,
      "follower_count": 4000,
      "smart_follower_count": 4,
      "insightfullness": null,
      "originality": null
    },
    {
      "id": 51351548,
      "name": "币世王 ｜MemeMax⚡️",
      "rank": 68,
      "user_id": "-1",
      "topic_id": "INFERENCELABS",
      "username": "0xKingsKuan",
      "mindshare": 0.38,
      "projectId": 341,
      "duration": "7D",
      "updatedAt": 1765065523721,
      "follower_count": 58346,
      "smart_follower_count": 300,
      "insightfullness": null,
      "originality": null
    },
    {
      "id": 51351549,
      "name": "Bitcoinboy ၊(🍊,💊) 🍪 Snapper",
      "rank": 69,
      "user_id": "-1",
      "topic_id": "INFERENCELABS",
      "username": "Bitcoinboy81880",
      "mindshare": 0.37,
      "projectId": 341,
      "duration": "7D",
      "updatedAt": 1765065523721,
      "follower_count": 2414,
      "smart_follower_count": 3,
      "insightfullness": null,
      "originality": null
    },
    {
      "id": 51351550,
      "name": "Mizzella",
      "rank": 70,
      "user_id": "-1",
      "topic_id": "INFERENCELABS",
      "username": "mizzelaalphax",
      "mindshare": 0.37,
      "projectId": 341,
      "duration": "7D",
      "updatedAt": 1765065523721,
      "follower_count": 4730,
      "smart_follower_count": 24,
      "insightfullness": null,
      "originality": null
    },
    {
      "id": 51351551,
      "name": "Portgas Ace | 🧠SENT",
      "rank": 71,
      "user_id": "-1",
      "topic_id": "INFERENCELABS",
      "username": "Ace_dz01",
      "mindshare": 0.36,
      "projectId": 341,
      "duration": "7D",
      "updatedAt": 1765065523721,
      "follower_count": 1847,
      "smart_follower_count": 22,
      "insightfullness": null,
      "originality": null
    },
    {
      "id": 51351552,
      "name": "fortifiedlonger",
      "rank": 72,
      "user_id": "-1",
      "topic_id": "INFERENCELABS",
      "username": "_justchck",
      "mindshare": 0.36,
      "projectId": 341,
      "duration": "7D",
      "updatedAt": 1765065523721,
      "follower_count": 1359,
      "smart_follower_count": 1,
      "insightfullness": null,
      "originality": null
    },
    {
      "id": 51351553,
      "name": "Diesel",
      "rank": 73,
      "user_id": "-1",
      "topic_id": "INFERENCELABS",
      "username": "0xdiesell",
      "mindshare": 0.36,
      "projectId": 341,
      "duration": "7D",
      "updatedAt": 1765065523721,
      "follower_count": 1088,
      "smart_follower_count": 1,
      "insightfullness": null,
      "originality": null
    },
    {
      "id": 51351554,
      "name": "Arlo🎋",
      "rank": 74,
      "user_id": "-1",
      "topic_id": "INFERENCELABS",
      "username": "Habib_XYZ8",
      "mindshare": 0.35,
      "projectId": 341,
      "duration": "7D",
      "updatedAt": 1765065523721,
      "follower_count": 3232,
      "smart_follower_count": 4,
      "insightfullness": null,
      "originality": null
    },
    {
      "id": 51351555,
      "name": "ÀBÁYÒMÍ",
      "rank": 75,
      "user_id": "-1",
      "topic_id": "INFERENCELABS",
      "username": "YomeeShuga",
      "mindshare": 0.34,
      "projectId": 341,
      "duration": "7D",
      "updatedAt": 1765065523721,
      "follower_count": 4935,
      "smart_follower_count": 26,
      "insightfullness": null,
      "originality": null
    },
    {
      "id": 51351556,
      "name": "小智🧠SENT",
      "rank": 76,
      "user_id": "-1",
      "topic_id": "INFERENCELABS",
      "username": "XiaoZhi_BTC",
      "mindshare": 0.34,
      "projectId": 341,
      "duration": "7D",
      "updatedAt": 1765065523721,
      "follower_count": 12187,
      "smart_follower_count": 56,
      "insightfullness": null,
      "originality": null
    },
    {
      "id": 51351557,
      "name": "MAPUING | MemeMax⚡️",
      "rank": 77,
      "user_id": "-1",
      "topic_id": "INFERENCELABS",
      "username": "awwa_367",
      "mindshare": 0.33,
      "projectId": 341,
      "duration": "7D",
      "updatedAt": 1765065523721,
      "follower_count": 3154,
      "smart_follower_count": 114,
      "insightfullness": null,
      "originality": null
    },
    {
      "id": 51351558,
      "name": "Ali Taimoor",
      "rank": 78,
      "user_id": "-1",
      "topic_id": "INFERENCELABS",
      "username": "alitaimoor07",
      "mindshare": 0.33,
      "projectId": 341,
      "duration": "7D",
      "updatedAt": 1765065523721,
      "follower_count": 2862,
      "smart_follower_count": 5,
      "insightfullness": null,
      "originality": null
    },
    {
      "id": 51351559,
      "name": "Crocy_MemeMax⚡️",
      "rank": 79,
      "user_id": "-1",
      "topic_id": "INFERENCELABS",
      "username": "0xCrocy",
      "mindshare": 0.32,
      "projectId": 341,
      "duration": "7D",
      "updatedAt": 1765065523721,
      "follower_count": 25559,
      "smart_follower_count": 252,
      "insightfullness": null,
      "originality": null
    },
    {
      "id": 51351560,
      "name": "0XGIWA",
      "rank": 80,
      "user_id": "-1",
      "topic_id": "INFERENCELABS",
      "username": "0xGiwax",
      "mindshare": 0.31,
      "projectId": 341,
      "duration": "7D",
      "updatedAt": 1765065523721,
      "follower_count": 5203,
      "smart_follower_count": 84,
      "insightfullness": null,
      "originality": null
    },
    {
      "id": 51351561,
      "name": "Cryptomaster ⌘🛠",
      "rank": 81,
      "user_id": "-1",
      "topic_id": "INFERENCELABS",
      "username": "FELIXBONIFACE2",
      "mindshare": 0.31,
      "projectId": 341,
      "duration": "7D",
      "updatedAt": 1765065523721,
      "follower_count": 4742,
      "smart_follower_count": 15,
      "insightfullness": null,
      "originality": null
    },
    {
      "id": 51351562,
      "name": "Daddyyoo",
      "rank": 82,
      "user_id": "-1",
      "topic_id": "INFERENCELABS",
      "username": "daddyyoo99",
      "mindshare": 0.31,
      "projectId": 341,
      "duration": "7D",
      "updatedAt": 1765065523721,
      "follower_count": 2072,
      "smart_follower_count": 2,
      "insightfullness": null,
      "originality": null
    },
    {
      "id": 51351563,
      "name": "Diego",
      "rank": 83,
      "user_id": "-1",
      "topic_id": "INFERENCELABS",
      "username": "diego_defai",
      "mindshare": 0.31,
      "projectId": 341,
      "duration": "7D",
      "updatedAt": 1765065523721,
      "follower_count": 6176,
      "smart_follower_count": 224,
      "insightfullness": null,
      "originality": null
    },
    {
      "id": 51351564,
      "name": "Vjt",
      "rank": 84,
      "user_id": "-1",
      "topic_id": "INFERENCELABS",
      "username": "vjtonway",
      "mindshare": 0.3,
      "projectId": 341,
      "duration": "7D",
      "updatedAt": 1765065523721,
      "follower_count": 5512,
      "smart_follower_count": 32,
      "insightfullness": null,
      "originality": null
    },
    {
      "id": 51351565,
      "name": "Rollup Guy",
      "rank": 85,
      "user_id": "-1",
      "topic_id": "INFERENCELABS",
      "username": "RollupGuy26",
      "mindshare": 0.29,
      "projectId": 341,
      "duration": "7D",
      "updatedAt": 1765065523721,
      "follower_count": 1783,
      "smart_follower_count": 20,
      "insightfullness": null,
      "originality": null
    },
    {
      "id": 51351566,
      "name": "Leo.Master.MemeMax ⚡️",
      "rank": 86,
      "user_id": "-1",
      "topic_id": "INFERENCELABS",
      "username": "ezeroho8245",
      "mindshare": 0.29,
      "projectId": 341,
      "duration": "7D",
      "updatedAt": 1765065523721,
      "follower_count": 11586,
      "smart_follower_count": 128,
      "insightfullness": null,
      "originality": null
    },
    {
      "id": 51351567,
      "name": "steelorian | MemeMax⚡️",
      "rank": 87,
      "user_id": "-1",
      "topic_id": "INFERENCELABS",
      "username": "steelorian",
      "mindshare": 0.29,
      "projectId": 341,
      "duration": "7D",
      "updatedAt": 1765065523721,
      "follower_count": 11045,
      "smart_follower_count": 210,
      "insightfullness": null,
      "originality": null
    },
    {
      "id": 51351568,
      "name": "Osorry | MemeMax⚡️",
      "rank": 88,
      "user_id": "-1",
      "topic_id": "INFERENCELABS",
      "username": "OsorryKor",
      "mindshare": 0.29,
      "projectId": 341,
      "duration": "7D",
      "updatedAt": 1765065523721,
      "follower_count": 3506,
      "smart_follower_count": 78,
      "insightfullness": null,
      "originality": null
    },
    {
      "id": 51351569,
      "name": "Toffees ∞ KIN (❖,❖)",
      "rank": 89,
      "user_id": "-1",
      "topic_id": "INFERENCELABS",
      "username": "q2q2cc",
      "mindshare": 0.28,
      "projectId": 341,
      "duration": "7D",
      "updatedAt": 1765065523721,
      "follower_count": 2823,
      "smart_follower_count": 61,
      "insightfullness": null,
      "originality": null
    },
    {
      "id": 51351570,
      "name": "람쥐썬더 Ramz / ∞ KIN / MemeMax⚡️",
      "rank": 90,
      "user_id": "-1",
      "topic_id": "INFERENCELABS",
      "username": "ramztd",
      "mindshare": 0.28,
      "projectId": 341,
      "duration": "7D",
      "updatedAt": 1765065523721,
      "follower_count": 3289,
      "smart_follower_count": 114,
      "insightfullness": null,
      "originality": null
    },
    {
      "id": 51351571,
      "name": "SPARROW",
      "rank": 91,
      "user_id": "-1",
      "topic_id": "INFERENCELABS",
      "username": "WEB3_SPARROWs",
      "mindshare": 0.28,
      "projectId": 341,
      "duration": "7D",
      "updatedAt": 1765065523721,
      "follower_count": 619,
      "smart_follower_count": 1,
      "insightfullness": null,
      "originality": null
    },
    {
      "id": 51351572,
      "name": "Sati_국제백수 | MemeMax⚡️|.edge🦭|🌊RIVER | ∞ KIN",
      "rank": 92,
      "user_id": "-1",
      "topic_id": "INFERENCELABS",
      "username": "firedc0",
      "mindshare": 0.27,
      "projectId": 341,
      "duration": "7D",
      "updatedAt": 1765065523721,
      "follower_count": 2337,
      "smart_follower_count": 47,
      "insightfullness": null,
      "originality": null
    },
    {
      "id": 51351573,
      "name": "Tboss 𝔽rAI",
      "rank": 93,
      "user_id": "-1",
      "topic_id": "INFERENCELABS",
      "username": "tbossx5",
      "mindshare": 0.27,
      "projectId": 341,
      "duration": "7D",
      "updatedAt": 1765065523721,
      "follower_count": 1170,
      "smart_follower_count": 2,
      "insightfullness": null,
      "originality": null
    },
    {
      "id": 51351574,
      "name": "S.B",
      "rank": 94,
      "user_id": "-1",
      "topic_id": "INFERENCELABS",
      "username": "sourchocoo",
      "mindshare": 0.26,
      "projectId": 341,
      "duration": "7D",
      "updatedAt": 1765065523721,
      "follower_count": 2554,
      "smart_follower_count": 73,
      "insightfullness": null,
      "originality": null
    },
    {
      "id": 51351575,
      "name": "Bayonle🕊️",
      "rank": 95,
      "user_id": "-1",
      "topic_id": "INFERENCELABS",
      "username": "adeniyiontwit",
      "mindshare": 0.26,
      "projectId": 341,
      "duration": "7D",
      "updatedAt": 1765065523721,
      "follower_count": 2528,
      "smart_follower_count": 8,
      "insightfullness": null,
      "originality": null
    },
    {
      "id": 51351576,
      "name": "arabom0.싸이식 | GAIB 🟠 MemeMax⚡️(❖,❖)",
      "rank": 96,
      "user_id": "-1",
      "topic_id": "INFERENCELABS",
      "username": "arabom0",
      "mindshare": 0.26,
      "projectId": 341,
      "duration": "7D",
      "updatedAt": 1765065523721,
      "follower_count": 1870,
      "smart_follower_count": 34,
      "insightfullness": null,
      "originality": null
    },
    {
      "id": 51351577,
      "name": "Quiet.eth",
      "rank": 97,
      "user_id": "-1",
      "topic_id": "INFERENCELABS",
      "username": "Quiet_eth1",
      "mindshare": 0.26,
      "projectId": 341,
      "duration": "7D",
      "updatedAt": 1765065523721,
      "follower_count": 2395,
      "smart_follower_count": 5,
      "insightfullness": null,
      "originality": null
    },
    {
      "id": 51351578,
      "name": "AxiomNode9",
      "rank": 98,
      "user_id": "-1",
      "topic_id": "INFERENCELABS",
      "username": "MANkol181777",
      "mindshare": 0.26,
      "projectId": 341,
      "duration": "7D",
      "updatedAt": 1765065523721,
      "follower_count": 996,
      "smart_follower_count": 1,
      "insightfullness": null,
      "originality": null
    },
    {
      "id": 51794588,
      "name": "Zɑrk",
      "rank": 99,
      "user_id": "-1",
      "topic_id": "INFERENCELABS",
      "username": "zarkbns",
      "mindshare": 0.26,
      "projectId": 341,
      "duration": "7D",
      "updatedAt": 1765065523721,
      "follower_count": 856,
      "smart_follower_count": 1,
      "insightfullness": null,
      "originality": null
    }
  ]
}