{
  "data": [
    {
      "id": 3824891,
      "name": "A₿del ∞/21M",
      "rank": 1,
      "user_id": "-1",
      "topic_id": "STARKNET",
      "username": "dimahledba",
      "mindshare": 8.03,
      "projectId": 62,
      "duration": "30D",
      "updatedAt": 1762860332776,
      "follower_count": 30471,
      "smart_follower_count": 1116,
      "insightfullness": null,
      "originality": null
    },
    {
      "id": 3824892,
      "name": "Eli Ben-Sasson | Starknet.io",
      "rank": 2,
      "user_id": "-1",
      "topic_id": "STARKNET",
      "username": "EliBenSasson",
      "mindshare": 5.7,
      "projectId": 62,
      "duration": "30D",
      "updatedAt": 1762860332776,
      "follower_count": 46226,
      "smart_follower_count": 2550,
      "insightfullness": null,
      "originality": null
    },
    {
      "id": 3824893,
      "name": "Brother Odin",
      "rank": 3,
      "user_id": "-1",
      "topic_id": "STARKNET",
      "username": "odin_free",
      "mindshare": 5.06,
      "projectId": 62,
      "duration": "30D",
      "updatedAt": 1762860332776,
      "follower_count": 37646,
      "smart_follower_count": 1282,
      "insightfullness": null,
      "originality": null
    },
    {
      "id": 3824894,
      "name": "Brother Lyskey",
      "rank": 4,
      "user_id": "-1",
      "topic_id": "STARKNET",
      "username": "Lyskey",
      "mindshare": 3.96,
      "projectId": 62,
      "duration": "30D",
      "updatedAt": 1762860332776,
      "follower_count": 11601,
      "smart_follower_count": 293,
      "insightfullness": null,
      "originality": null
    },
    {
      "id": 3824895,
      "name": "Benjamin Sturisky",
      "rank": 5,
      "user_id": "-1",
      "topic_id": "STARKNET",
      "username": "bsturisky",
      "mindshare": 2.65,
      "projectId": 62,
      "duration": "30D",
      "updatedAt": 1762860332776,
      "follower_count": 3155,
      "smart_follower_count": 404,
      "insightfullness": null,
      "originality": null
    },
    {
      "id": 3824896,
      "name": "Mentor zReka ✨",
      "rank": 6,
      "user_id": "-1",
      "topic_id": "STARKNET",
      "username": "MentorNotPseudo",
      "mindshare": 2.63,
      "projectId": 62,
      "duration": "30D",
      "updatedAt": 1762860332776,
      "follower_count": 3549,
      "smart_follower_count": 241,
      "insightfullness": null,
      "originality": null
    },
    {
      "id": 3824897,
      "name": "Tindorr 🌯",
      "rank": 7,
      "user_id": "-1",
      "topic_id": "STARKNET",
      "username": "0xTindorr",
      "mindshare": 1.91,
      "projectId": 62,
      "duration": "30D",
      "updatedAt": 1762860332776,
      "follower_count": 44692,
      "smart_follower_count": 849,
      "insightfullness": null,
      "originality": null
    },
    {
      "id": 3824898,
      "name": "Fede’s intern 🥊",
      "rank": 8,
      "user_id": "-1",
      "topic_id": "STARKNET",
      "username": "fede_intern",
      "mindshare": 1.88,
      "projectId": 62,
      "duration": "30D",
      "updatedAt": 1762860332776,
      "follower_count": 49947,
      "smart_follower_count": 2070,
      "insightfullness": null,
      "originality": null
    },
    {
      "id": 3824899,
      "name": "Ohad Barta",
      "rank": 9,
      "user_id": "-1",
      "topic_id": "STARKNET",
      "username": "OhadBarta",
      "mindshare": 1.82,
      "projectId": 62,
      "duration": "30D",
      "updatedAt": 1762860332776,
      "follower_count": 1449,
      "smart_follower_count": 193,
      "insightfullness": null,
      "originality": null
    },
    {
      "id": 3824900,
      "name": "brother victor",
      "rank": 10,
      "user_id": "-1",
      "topic_id": "STARKNET",
      "username": "starkience",
      "mindshare": 1.23,
      "projectId": 62,
      "duration": "30D",
      "updatedAt": 1762860332776,
      "follower_count": 2183,
      "smart_follower_count": 159,
      "insightfullness": null,
      "originality": null
    },
    {
      "id": 3824901,
      "name": "hitesh.eth",
      "rank": 11,
      "user_id": "-1",
      "topic_id": "STARKNET",
      "username": "hmalviya9",
      "mindshare": 1.03,
      "projectId": 62,
      "duration": "30D",
      "updatedAt": 1762860332776,
      "follower_count": 88646,
      "smart_follower_count": 1638,
      "insightfullness": null,
      "originality": null
    },
    {
      "id": 3824902,
      "name": "Vladezy",
      "rank": 12,
      "user_id": "-1",
      "topic_id": "STARKNET",
      "username": "vladezy_",
      "mindshare": 0.98,
      "projectId": 62,
      "duration": "30D",
      "updatedAt": 1762860332776,
      "follower_count": 338,
      "smart_follower_count": 26,
      "insightfullness": null,
      "originality": null
    },
    {
      "id": 3824903,
      "name": "teddy",
      "rank": 13,
      "user_id": "-1",
      "topic_id": "STARKNET",
      "username": "franklyteddy",
      "mindshare": 0.83,
      "projectId": 62,
      "duration": "30D",
      "updatedAt": 1762860332776,
      "follower_count": 3264,
      "smart_follower_count": 158,
      "insightfullness": null,
      "originality": null
    },
    {
      "id": 3824904,
      "name": "materkel.eth 🦇🔊",
      "rank": 14,
      "user_id": "-1",
      "topic_id": "STARKNET",
      "username": "materkel",
      "mindshare": 0.82,
      "projectId": 62,
      "duration": "30D",
      "updatedAt": 1762860332776,
      "follower_count": 5071,
      "smart_follower_count": 259,
      "insightfullness": null,
      "originality": null
    },
    {
      "id": 3824905,
      "name": "Omar Espejel (BTCFi arc)",
      "rank": 15,
      "user_id": "-1",
      "topic_id": "STARKNET",
      "username": "espejelomar",
      "mindshare": 0.82,
      "projectId": 62,
      "duration": "30D",
      "updatedAt": 1762860332776,
      "follower_count": 3079,
      "smart_follower_count": 165,
      "insightfullness": null,
      "originality": null
    },
    {
      "id": 3824906,
      "name": "Brother Akash Balasubramani 🐺🔊",
      "rank": 16,
      "user_id": "-1",
      "topic_id": "STARKNET",
      "username": "akashneelesh",
      "mindshare": 0.78,
      "projectId": 62,
      "duration": "30D",
      "updatedAt": 1762860332776,
      "follower_count": 2726,
      "smart_follower_count": 138,
      "insightfullness": null,
      "originality": null
    },
    {
      "id": 3824907,
      "name": "Calc.eth",
      "rank": 17,
      "user_id": "-1",
      "topic_id": "STARKNET",
      "username": "Calcutat",
      "mindshare": 0.76,
      "projectId": 62,
      "duration": "30D",
      "updatedAt": 1762860332776,
      "follower_count": 2188,
      "smart_follower_count": 200,
      "insightfullness": null,
      "originality": null
    },
    {
      "id": 3824908,
      "name": "Nurstar 🐺✨🐱",
      "rank": 18,
      "user_id": "-1",
      "topic_id": "STARKNET",
      "username": "0xNurstar",
      "mindshare": 0.72,
      "projectId": 62,
      "duration": "30D",
      "updatedAt": 1762860332776,
      "follower_count": 8230,
      "smart_follower_count": 445,
      "insightfullness": null,
      "originality": null
    },
    {
      "id": 3824909,
      "name": "zerokn0wledge.hl 🪬✨",
      "rank": 19,
      "user_id": "-1",
      "topic_id": "STARKNET",
      "username": "zerokn0wledge_",
      "mindshare": 0.65,
      "projectId": 62,
      "duration": "30D",
      "updatedAt": 1762860332776,
      "follower_count": 27047,
      "smart_follower_count": 978,
      "insightfullness": null,
      "originality": null
    },
    {
      "id": 3824910,
      "name": "Eugene Bulltime🕯️",
      "rank": 20,
      "user_id": "-1",
      "topic_id": "STARKNET",
      "username": "Eugene_Bulltime",
      "mindshare": 0.64,
      "projectId": 62,
      "duration": "30D",
      "updatedAt": 1762860332776,
      "follower_count": 3907,
      "smart_follower_count": 211,
      "insightfullness": null,
      "originality": null
    },
    {
      "id": 3824911,
      "name": "shadowfax",
      "rank": 21,
      "user_id": "-1",
      "topic_id": "STARKNET",
      "username": "heyshadowfax",
      "mindshare": 0.5,
      "projectId": 62,
      "duration": "30D",
      "updatedAt": 1762860332776,
      "follower_count": 2512,
      "smart_follower_count": 216,
      "insightfullness": null,
      "originality": null
    },
    {
      "id": 3824912,
      "name": "Dylan Kugler (BTCFi arc)",
      "rank": 22,
      "user_id": "-1",
      "topic_id": "STARKNET",
      "username": "dylankugler",
      "mindshare": 0.5,
      "projectId": 62,
      "duration": "30D",
      "updatedAt": 1762860332776,
      "follower_count": 1972,
      "smart_follower_count": 211,
      "insightfullness": null,
      "originality": null
    },
    {
      "id": 3824913,
      "name": "The Advisor.btc 🟧",
      "rank": 23,
      "user_id": "-1",
      "topic_id": "STARKNET",
      "username": "theadvisorbtc",
      "mindshare": 0.49,
      "projectId": 62,
      "duration": "30D",
      "updatedAt": 1762860332776,
      "follower_count": 5386,
      "smart_follower_count": 279,
      "insightfullness": null,
      "originality": null
    },
    {
      "id": 3824914,
      "name": "TVBee.edge🦭MemeMax ⚡️",
      "rank": 24,
      "user_id": "-1",
      "topic_id": "STARKNET",
      "username": "blockTVBee",
      "mindshare": 0.48,
      "projectId": 62,
      "duration": "30D",
      "updatedAt": 1762860332776,
      "follower_count": 27601,
      "smart_follower_count": 263,
      "insightfullness": null,
      "originality": null
    },
    {
      "id": 3824915,
      "name": "The Crypto Professor",
      "rank": 25,
      "user_id": "-1",
      "topic_id": "STARKNET",
      "username": "TheCryptoProfes",
      "mindshare": 0.48,
      "projectId": 62,
      "duration": "30D",
      "updatedAt": 1762860332776,
      "follower_count": 37817,
      "smart_follower_count": 230,
      "insightfullness": null,
      "originality": null
    },
    {
      "id": 3824916,
      "name": "Rehan Nek",
      "rank": 26,
      "user_id": "-1",
      "topic_id": "STARKNET",
      "username": "RehanNek",
      "mindshare": 0.46,
      "projectId": 62,
      "duration": "30D",
      "updatedAt": 1762860332776,
      "follower_count": 1145,
      "smart_follower_count": 97,
      "insightfullness": null,
      "originality": null
    },
    {
      "id": 3824917,
      "name": "Sizero",
      "rank": 27,
      "user_id": "-1",
      "topic_id": "STARKNET",
      "username": "Sizero",
      "mindshare": 0.45,
      "projectId": 62,
      "duration": "30D",
      "updatedAt": 1762860332776,
      "follower_count": 704,
      "smart_follower_count": 64,
      "insightfullness": null,
      "originality": null
    },
    {
      "id": 3824918,
      "name": "Djani",
      "rank": 28,
      "user_id": "-1",
      "topic_id": "STARKNET",
      "username": "DjaniWhaleSkul",
      "mindshare": 0.45,
      "projectId": 62,
      "duration": "30D",
      "updatedAt": 1762860332776,
      "follower_count": 8781,
      "smart_follower_count": 183,
      "insightfullness": null,
      "originality": null
    },
    {
      "id": 3824919,
      "name": "Brother CryptoTraalala.stark",
      "rank": 29,
      "user_id": "-1",
      "topic_id": "STARKNET",
      "username": "CryptoTraalala",
      "mindshare": 0.39,
      "projectId": 62,
      "duration": "30D",
      "updatedAt": 1762860332776,
      "follower_count": 3181,
      "smart_follower_count": 67,
      "insightfullness": null,
      "originality": null
    },
    {
      "id": 3824920,
      "name": "Rektnomist",
      "rank": 30,
      "user_id": "-1",
      "topic_id": "STARKNET",
      "username": "rektonomist_",
      "mindshare": 0.39,
      "projectId": 62,
      "duration": "30D",
      "updatedAt": 1762860332776,
      "follower_count": 28280,
      "smart_follower_count": 481,
      "insightfullness": null,
      "originality": null
    },
    {
      "id": 3824921,
      "name": "Eli5DeFi",
      "rank": 31,
      "user_id": "-1",
      "topic_id": "STARKNET",
      "username": "eli5_defi",
      "mindshare": 0.38,
      "projectId": 62,
      "duration": "30D",
      "updatedAt": 1762860332776,
      "follower_count": 42806,
      "smart_follower_count": 1000,
      "insightfullness": null,
      "originality": null
    },
    {
      "id": 3824922,
      "name": "Chanimal 🍌 $APE 🦍 Noya",
      "rank": 32,
      "user_id": "-1",
      "topic_id": "STARKNET",
      "username": "JaysonCrypto",
      "mindshare": 0.38,
      "projectId": 62,
      "duration": "30D",
      "updatedAt": 1762860332776,
      "follower_count": 24033,
      "smart_follower_count": 1607,
      "insightfullness": null,
      "originality": null
    },
    {
      "id": 3824923,
      "name": "Nadai",
      "rank": 33,
      "user_id": "-1",
      "topic_id": "STARKNET",
      "username": "Nadai02010",
      "mindshare": 0.32,
      "projectId": 62,
      "duration": "30D",
      "updatedAt": 1762860332776,
      "follower_count": 1093,
      "smart_follower_count": 67,
      "insightfullness": null,
      "originality": null
    },
    {
      "id": 3824924,
      "name": "DeFi Warhol",
      "rank": 34,
      "user_id": "-1",
      "topic_id": "STARKNET",
      "username": "Defi_Warhol",
      "mindshare": 0.31,
      "projectId": 62,
      "duration": "30D",
      "updatedAt": 1762860332776,
      "follower_count": 34101,
      "smart_follower_count": 566,
      "insightfullness": null,
      "originality": null
    },
    {
      "id": 3824925,
      "name": "rf.extended",
      "rank": 35,
      "user_id": "-1",
      "topic_id": "STARKNET",
      "username": "rf_extended",
      "mindshare": 0.25,
      "projectId": 62,
      "duration": "30D",
      "updatedAt": 1762860332776,
      "follower_count": 3314,
      "smart_follower_count": 199,
      "insightfullness": null,
      "originality": null
    },
    {
      "id": 3824926,
      "name": "Maxlion🦁",
      "rank": 36,
      "user_id": "-1",
      "topic_id": "STARKNET",
      "username": "Real_Maxlion",
      "mindshare": 0.22,
      "projectId": 62,
      "duration": "30D",
      "updatedAt": 1762860332776,
      "follower_count": 9745,
      "smart_follower_count": 258,
      "insightfullness": null,
      "originality": null
    },
    {
      "id": 3824927,
      "name": "Udon🍜うどん(🌸, 🌿) | ∞ KIN",
      "rank": 37,
      "user_id": "-1",
      "topic_id": "STARKNET",
      "username": "egyptk6",
      "mindshare": 0.21,
      "projectId": 62,
      "duration": "30D",
      "updatedAt": 1762860332776,
      "follower_count": 44411,
      "smart_follower_count": 227,
      "insightfullness": null,
      "originality": null
    },
    {
      "id": 3824928,
      "name": "Web3｜龙猫 MemeMax⚡️",
      "rank": 38,
      "user_id": "-1",
      "topic_id": "STARKNET",
      "username": "liaoblove520",
      "mindshare": 0.21,
      "projectId": 62,
      "duration": "30D",
      "updatedAt": 1762860332776,
      "follower_count": 67932,
      "smart_follower_count": 95,
      "insightfullness": null,
      "originality": null
    },
    {
      "id": 3824929,
      "name": "monero-chang 🧪",
      "rank": 39,
      "user_id": "-1",
      "topic_id": "STARKNET",
      "username": "chang_defi",
      "mindshare": 0.21,
      "projectId": 62,
      "duration": "30D",
      "updatedAt": 1762860332776,
      "follower_count": 17117,
      "smart_follower_count": 1372,
      "insightfullness": null,
      "originality": null
    },
    {
      "id": 3824930,
      "name": "Koob (T) 쿠쿠쿱 (T) | 𝔽rAI",
      "rank": 40,
      "user_id": "-1",
      "topic_id": "STARKNET",
      "username": "kimyg002",
      "mindshare": 0.19,
      "projectId": 62,
      "duration": "30D",
      "updatedAt": 1762860332776,
      "follower_count": 16518,
      "smart_follower_count": 345,
      "insightfullness": null,
      "originality": null
    },
    {
      "id": 3824931,
      "name": "Henri (BTCFi arc)",
      "rank": 41,
      "user_id": "-1",
      "topic_id": "STARKNET",
      "username": "henrlihenrli",
      "mindshare": 0.18,
      "projectId": 62,
      "duration": "30D",
      "updatedAt": 1762860332776,
      "follower_count": 9068,
      "smart_follower_count": 582,
      "insightfullness": null,
      "originality": null
    },
    {
      "id": 3824932,
      "name": "Brother Eruk (brain/acc)",
      "rank": 42,
      "user_id": "-1",
      "topic_id": "STARKNET",
      "username": "syaerulid",
      "mindshare": 0.17,
      "projectId": 62,
      "duration": "30D",
      "updatedAt": 1762860332776,
      "follower_count": 3521,
      "smart_follower_count": 38,
      "insightfullness": null,
      "originality": null
    },
    {
      "id": 3824933,
      "name": "A1 Research",
      "rank": 43,
      "user_id": "-1",
      "topic_id": "STARKNET",
      "username": "a1research__",
      "mindshare": 0.17,
      "projectId": 62,
      "duration": "30D",
      "updatedAt": 1762860332776,
      "follower_count": 9743,
      "smart_follower_count": 534,
      "insightfullness": null,
      "originality": null
    },
    {
      "id": 3824934,
      "name": "robert (BTCFi arc)",
      "rank": 44,
      "user_id": "-1",
      "topic_id": "STARKNET",
      "username": "robertkp13",
      "mindshare": 0.17,
      "projectId": 62,
      "duration": "30D",
      "updatedAt": 1762860332776,
      "follower_count": 1808,
      "smart_follower_count": 139,
      "insightfullness": null,
      "originality": null
    },
    {
      "id": 3824935,
      "name": "katexbt.hl",
      "rank": 45,
      "user_id": "-1",
      "topic_id": "STARKNET",
      "username": "katexbt",
      "mindshare": 0.16,
      "projectId": 62,
      "duration": "30D",
      "updatedAt": 1762860332776,
      "follower_count": 24405,
      "smart_follower_count": 1152,
      "insightfullness": null,
      "originality": null
    },
    {
      "id": 3824936,
      "name": "Chris",
      "rank": 46,
      "user_id": "-1",
      "topic_id": "STARKNET",
      "username": "lechriss17",
      "mindshare": 0.13,
      "projectId": 62,
      "duration": "30D",
      "updatedAt": 1762860332776,
      "follower_count": 7007,
      "smart_follower_count": 164,
      "insightfullness": null,
      "originality": null
    },
    {
      "id": 3824937,
      "name": "BLEDI",
      "rank": 47,
      "user_id": "-1",
      "topic_id": "STARKNET",
      "username": "bledi_ai",
      "mindshare": 0.13,
      "projectId": 62,
      "duration": "30D",
      "updatedAt": 1762860332776,
      "follower_count": 52317,
      "smart_follower_count": 338,
      "insightfullness": null,
      "originality": null
    },
    {
      "id": 3824938,
      "name": "ollie",
      "rank": 48,
      "user_id": "-1",
      "topic_id": "STARKNET",
      "username": "olliegarch",
      "mindshare": 0.11,
      "projectId": 62,
      "duration": "30D",
      "updatedAt": 1762860332776,
      "follower_count": 1367,
      "smart_follower_count": 149,
      "insightfullness": null,
      "originality": null
    },
    {
      "id": 21858352,
      "name": "Adam Livingston",
      "rank": 49,
      "user_id": "-1",
      "topic_id": "STARKNET",
      "username": "AdamBLiv",
      "mindshare": 0.11,
      "projectId": 62,
      "duration": "30D",
      "updatedAt": 1762860332776,
      "follower_count": 61463,
      "smart_follower_count": 274,
      "insightfullness": null,
      "originality": null
    },
    {
      "id": 21980409,
      "name": "yyy",
      "rank": 50,
      "user_id": "-1",
      "topic_id": "STARKNET",
      "username": "y_cryptoanalyst",
      "mindshare": 0.1,
      "projectId": 62,
      "duration": "30D",
      "updatedAt": 1762860332776,
      "follower_count": 25040,
      "smart_follower_count": 357,
      "insightfullness": null,
      "originality": null
    },
    {
      "id": 22183611,
      "name": "Brother 0D3d (BTCFi arc)🐺",
      "rank": 51,
      "user_id": "-1",
      "topic_id": "STARKNET",
      "username": "odedonn",
      "mindshare": 0.09,
      "projectId": 62,
      "duration": "30D",
      "updatedAt": 1762860332776,
      "follower_count": 744,
      "smart_follower_count": 74,
      "insightfullness": null,
      "originality": null
    },
    {
      "id": 22386077,
      "name": "ducky",
      "rank": 52,
      "user_id": "-1",
      "topic_id": "STARKNET",
      "username": "marketducky",
      "mindshare": 0.07,
      "projectId": 62,
      "duration": "30D",
      "updatedAt": 1762860332776,
      "follower_count": 3249,
      "smart_follower_count": 168,
      "insightfullness": null,
      "originality": null
    },
    {
      "id": 22548568,
      "name": "Rejamong.eth",
      "rank": 53,
      "user_id": "-1",
      "topic_id": "STARKNET",
      "username": "r2Jamong",
      "mindshare": 0.06,
      "projectId": 62,
      "duration": "30D",
      "updatedAt": 1762860332776,
      "follower_count": 13580,
      "smart_follower_count": 314,
      "insightfullness": null,
      "originality": null
    },
    {
      "id": 22751446,
      "name": "范特西.patron",
      "rank": 54,
      "user_id": "-1",
      "topic_id": "STARKNET",
      "username": "fantxu13637",
      "mindshare": 0.05,
      "projectId": 62,
      "duration": "30D",
      "updatedAt": 1762860332776,
      "follower_count": 3123,
      "smart_follower_count": 33,
      "insightfullness": null,
      "originality": null
    },
    {
      "id": 23520035,
      "name": "taka.eth",
      "rank": 55,
      "user_id": "-1",
      "topic_id": "STARKNET",
      "username": "taka_eth",
      "mindshare": 0.05,
      "projectId": 62,
      "duration": "30D",
      "updatedAt": 1762860332776,
      "follower_count": 13029,
      "smart_follower_count": 171,
      "insightfullness": null,
      "originality": null
    },
    {
      "id": 25756369,
      "name": "BTCFi Jonathan",
      "rank": 56,
      "user_id": "-1",
      "topic_id": "STARKNET",
      "username": "jyjonathan",
      "mindshare": 0.05,
      "projectId": 62,
      "duration": "30D",
      "updatedAt": 1762860332776,
      "follower_count": 113128,
      "smart_follower_count": 276,
      "insightfullness": null,
      "originality": null
    },
    {
      "id": 25955300,
      "name": "Auri",
      "rank": 57,
      "user_id": "-1",
      "topic_id": "STARKNET",
      "username": "Auri_0x",
      "mindshare": 0.05,
      "projectId": 62,
      "duration": "30D",
      "updatedAt": 1762860332776,
      "follower_count": 21148,
      "smart_follower_count": 906,
      "insightfullness": null,
      "originality": null
    },
    {
      "id": 26108643,
      "name": "Angela ☀️ (BTCFi arc)",
      "rank": 58,
      "user_id": "-1",
      "topic_id": "STARKNET",
      "username": "angela_s_n",
      "mindshare": 0.04,
      "projectId": 62,
      "duration": "30D",
      "updatedAt": 1762860332776,
      "follower_count": 2094,
      "smart_follower_count": 166,
      "insightfullness": null,
      "originality": null
    },
    {
      "id": 26799001,
      "name": "Josh Man",
      "rank": 59,
      "user_id": "-1",
      "topic_id": "STARKNET",
      "username": "JoshMandell6",
      "mindshare": 0.04,
      "projectId": 62,
      "duration": "30D",
      "updatedAt": 1762860332776,
      "follower_count": 148548,
      "smart_follower_count": 766,
      "insightfullness": null,
      "originality": null
    },
    {
      "id": 26799002,
      "name": "itamar",
      "rank": 60,
      "user_id": "-1",
      "topic_id": "STARKNET",
      "username": "itamarl",
      "mindshare": 0.03,
      "projectId": 62,
      "duration": "30D",
      "updatedAt": 1762860332776,
      "follower_count": 7570,
      "smart_follower_count": 791,
      "insightfullness": null,
      "originality": null
    },
    {
      "id": 38976656,
      "name": "Stacy Muur",
      "rank": 61,
      "user_id": "-1",
      "topic_id": "STARKNET",
      "username": "stacy_muur",
      "mindshare": 0.02,
      "projectId": 62,
      "duration": "30D",
      "updatedAt": 1762860332776,
      "follower_count": 72087,
      "smart_follower_count": 1589,
      "insightfullness": null,
      "originality": null
    },
    {
      "id": 39025168,
      "name": "pg",
      "rank": 62,
      "user_id": "-1",
      "topic_id": "STARKNET",
      "username": "pgreyy",
      "mindshare": 0.02,
      "projectId": 62,
      "duration": "30D",
      "updatedAt": 1762860332776,
      "follower_count": 8188,
      "smart_follower_count": 210,
      "insightfullness": null,
      "originality": null
    },
    {
      "id": 39025169,
      "name": "Dezarius",
      "rank": 63,
      "user_id": "-1",
      "topic_id": "STARKNET",
      "username": "nazarius_amb",
      "mindshare": 0.01,
      "projectId": 62,
      "duration": "30D",
      "updatedAt": 1762860332776,
      "follower_count": 1350,
      "smart_follower_count": 44,
      "insightfullness": null,
      "originality": null
    },
    {
      "id": 39025170,
      "name": "나지여(INowHere)🌊RIVER",
      "rank": 64,
      "user_id": "-1",
      "topic_id": "STARKNET",
      "username": "asiel86",
      "mindshare": 0.01,
      "projectId": 62,
      "duration": "30D",
      "updatedAt": 1762860332776,
      "follower_count": 3661,
      "smart_follower_count": 95,
      "insightfullness": null,
      "originality": null
    },
    {
      "id": 39025171,
      "name": "Marine (❖,❖)",
      "rank": 65,
      "user_id": "-1",
      "topic_id": "STARKNET",
      "username": "Crypto1Marine",
      "mindshare": 0.01,
      "projectId": 62,
      "duration": "30D",
      "updatedAt": 1762860332776,
      "follower_count": 4761,
      "smart_follower_count": 90,
      "insightfullness": null,
      "originality": null
    },
    {
      "id": 39122693,
      "name": "DAMBI",
      "rank": 66,
      "user_id": "-1",
      "topic_id": "STARKNET",
      "username": "doodlely213",
      "mindshare": 0.01,
      "projectId": 62,
      "duration": "30D",
      "updatedAt": 1762860332776,
      "follower_count": 5534,
      "smart_follower_count": 112,
      "insightfullness": null,
      "originality": null
    },
    {
      "id": 39398655,
      "name": "chainyoda",
      "rank": 67,
      "user_id": "-1",
      "topic_id": "STARKNET",
      "username": "chainyoda",
      "mindshare": 0.01,
      "projectId": 62,
      "duration": "30D",
      "updatedAt": 1762860332776,
      "follower_count": 41337,
      "smart_follower_count": 2750,
      "insightfullness": null,
      "originality": null
    },
    {
      "id": 39489766,
      "name": "Rory /✨🐐/",
      "rank": 68,
      "user_id": "-1",
      "topic_id": "STARKNET",
      "username": "0xRory",
      "mindshare": 0.01,
      "projectId": 62,
      "duration": "30D",
      "updatedAt": 1762860332776,
      "follower_count": 16617,
      "smart_follower_count": 227,
      "insightfullness": null,
      "originality": null
    },
    {
      "id": 39580569,
      "name": "SONJI.edge🦭",
      "rank": 69,
      "user_id": "-1",
      "topic_id": "STARKNET",
      "username": "_sonji",
      "mindshare": 0.01,
      "projectId": 62,
      "duration": "30D",
      "updatedAt": 1762860332776,
      "follower_count": 6617,
      "smart_follower_count": 131,
      "insightfullness": null,
      "originality": null
    }
  ]
}