{
  "data": [
    {
      "id": 3810911,
      "name": "BUKS",
      "rank": 1,
      "user_id": "-1",
      "topic_id": "IQ",
      "username": "vanillacrusz",
      "mindshare": 5.07,
      "projectId": 56,
      "duration": "30D",
      "updatedAt": 1761649801241,
      "follower_count": 4722,
      "smart_follower_count": 22,
      "insightfullness": null,
      "originality": null,
      "yaps_all": 15.04
    },
    {
      "id": 3810912,
      "name": "Gushydon",
      "rank": 2,
      "user_id": "-1",
      "topic_id": "IQ",
      "username": "Gushydon10",
      "mindshare": 5.03,
      "projectId": 56,
      "duration": "30D",
      "updatedAt": 1761649801241,
      "follower_count": 2221,
      "smart_follower_count": 22,
      "insightfullness": null,
      "originality": null,
      "yaps_all": 21.09
    },
    {
      "id": 3810913,
      "name": "jayplayco",
      "rank": 3,
      "user_id": "-1",
      "topic_id": "IQ",
      "username": "jayplayco",
      "mindshare": 4.75,
      "projectId": 56,
      "duration": "30D",
      "updatedAt": 1761649801241,
      "follower_count": 9350,
      "smart_follower_count": 273,
      "insightfullness": null,
      "originality": null,
      "yaps_all": 1301.75
    },
    {
      "id": 3810914,
      "name": "Sheikh Sulaiman | 𝔽rAI",
      "rank": 4,
      "user_id": "-1",
      "topic_id": "IQ",
      "username": "shaekh_sulaiman",
      "mindshare": 3.07,
      "projectId": 56,
      "duration": "30D",
      "updatedAt": 1761649801241,
      "follower_count": 750,
      "smart_follower_count": 4,
      "insightfullness": null,
      "originality": null,
      "yaps_all": null
    },
    {
      "id": 8191108,
      "name": "Uche Esther Ogechi.sign🧡🍊",
      "rank": 5,
      "user_id": "-1",
      "topic_id": "IQ",
      "username": "UcheEstherOgec1",
      "mindshare": 2.82,
      "projectId": 56,
      "duration": "30D",
      "updatedAt": 1761649801241,
      "follower_count": 1433,
      "smart_follower_count": 5,
      "insightfullness": null,
      "originality": null,
      "yaps_all": null
    },
    {
      "id": 8191109,
      "name": "cvendo.noya",
      "rank": 6,
      "user_id": "-1",
      "topic_id": "IQ",
      "username": "cvendo99",
      "mindshare": 2.21,
      "projectId": 56,
      "duration": "30D",
      "updatedAt": 1761649801241,
      "follower_count": 1745,
      "smart_follower_count": 10,
      "insightfullness": null,
      "originality": null,
      "yaps_all": 0.37
    },
    {
      "id": 8191110,
      "name": "CURRENCY",
      "rank": 7,
      "user_id": "-1",
      "topic_id": "IQ",
      "username": "dahirm000clone",
      "mindshare": 2.14,
      "projectId": 56,
      "duration": "30D",
      "updatedAt": 1761649801241,
      "follower_count": 1338,
      "smart_follower_count": 10,
      "insightfullness": null,
      "originality": null,
      "yaps_all": null
    },
    {
      "id": 8191111,
      "name": "Hearty | Someone You Love",
      "rank": 8,
      "user_id": "-1",
      "topic_id": "IQ",
      "username": "apostlehearty",
      "mindshare": 2.12,
      "projectId": 56,
      "duration": "30D",
      "updatedAt": 1761649801241,
      "follower_count": 4160,
      "smart_follower_count": 9,
      "insightfullness": null,
      "originality": null,
      "yaps_all": null
    },
    {
      "id": 8191112,
      "name": "Decrowntv1",
      "rank": 9,
      "user_id": "-1",
      "topic_id": "IQ",
      "username": "DecrownTV1",
      "mindshare": 2.05,
      "projectId": 56,
      "duration": "30D",
      "updatedAt": 1761649801241,
      "follower_count": 982,
      "smart_follower_count": 2,
      "insightfullness": null,
      "originality": null,
      "yaps_all": null
    },
    {
      "id": 8191113,
      "name": "Bella 🍑 🌺 Ⓜ️Ⓜ️T",
      "rank": 10,
      "user_id": "-1",
      "topic_id": "IQ",
      "username": "tesebellaa",
      "mindshare": 2.01,
      "projectId": 56,
      "duration": "30D",
      "updatedAt": 1761649801241,
      "follower_count": 2037,
      "smart_follower_count": 5,
      "insightfullness": null,
      "originality": null,
      "yaps_all": null
    },
    {
      "id": 8191114,
      "name": "kaycee Ⓜ️Ⓜ️T",
      "rank": 11,
      "user_id": "-1",
      "topic_id": "IQ",
      "username": "pohliteAnt",
      "mindshare": 1.67,
      "projectId": 56,
      "duration": "30D",
      "updatedAt": 1761649801241,
      "follower_count": 1937,
      "smart_follower_count": 10,
      "insightfullness": null,
      "originality": null,
      "yaps_all": null
    },
    {
      "id": 8191115,
      "name": "GODZILLA 🔥 💫",
      "rank": 12,
      "user_id": "-1",
      "topic_id": "IQ",
      "username": "Stephen48854211",
      "mindshare": 1.51,
      "projectId": 56,
      "duration": "30D",
      "updatedAt": 1761649801241,
      "follower_count": 1089,
      "smart_follower_count": 8,
      "insightfullness": null,
      "originality": null,
      "yaps_all": null
    },
    {
      "id": 8191116,
      "name": "Flancolindo",
      "rank": 13,
      "user_id": "-1",
      "topic_id": "IQ",
      "username": "lindo0308",
      "mindshare": 1.46,
      "projectId": 56,
      "duration": "30D",
      "updatedAt": 1761649801241,
      "follower_count": 4169,
      "smart_follower_count": 8,
      "insightfullness": null,
      "originality": null,
      "yaps_all": null
    },
    {
      "id": 8191117,
      "name": "Bitkevin(¤, ¤)",
      "rank": 14,
      "user_id": "-1",
      "topic_id": "IQ",
      "username": "Bitkevin1",
      "mindshare": 1.45,
      "projectId": 56,
      "duration": "30D",
      "updatedAt": 1761649801241,
      "follower_count": 881,
      "smart_follower_count": 58,
      "insightfullness": null,
      "originality": null,
      "yaps_all": null
    },
    {
      "id": 8191118,
      "name": "B.ely Creations",
      "rank": 15,
      "user_id": "-1",
      "topic_id": "IQ",
      "username": "lizzy_blhinkx",
      "mindshare": 1.35,
      "projectId": 56,
      "duration": "30D",
      "updatedAt": 1761649801241,
      "follower_count": 1093,
      "smart_follower_count": 1,
      "insightfullness": null,
      "originality": null,
      "yaps_all": null
    },
    {
      "id": 8191119,
      "name": "Nabeelahhh💕",
      "rank": 16,
      "user_id": "-1",
      "topic_id": "IQ",
      "username": "niniolaaaaa",
      "mindshare": 1.31,
      "projectId": 56,
      "duration": "30D",
      "updatedAt": 1761649801241,
      "follower_count": 3645,
      "smart_follower_count": 13,
      "insightfullness": null,
      "originality": null,
      "yaps_all": null
    },
    {
      "id": 8191120,
      "name": "Zenobrown! (✧ᴗ✧) Noya",
      "rank": 17,
      "user_id": "-1",
      "topic_id": "IQ",
      "username": "ZENOBROWN7",
      "mindshare": 1.27,
      "projectId": 56,
      "duration": "30D",
      "updatedAt": 1761649801241,
      "follower_count": 1222,
      "smart_follower_count": 6,
      "insightfullness": null,
      "originality": null,
      "yaps_all": null
    },
    {
      "id": 8191121,
      "name": "Aliyu Muhammad",
      "rank": 18,
      "user_id": "-1",
      "topic_id": "IQ",
      "username": "AMuhammad0814",
      "mindshare": 1.24,
      "projectId": 56,
      "duration": "30D",
      "updatedAt": 1761649801241,
      "follower_count": 246,
      "smart_follower_count": 1,
      "insightfullness": null,
      "originality": null,
      "yaps_all": null
    },
    {
      "id": 8191122,
      "name": "Anita V.",
      "rank": 19,
      "user_id": "-1",
      "topic_id": "IQ",
      "username": "RealAitia",
      "mindshare": 1.17,
      "projectId": 56,
      "duration": "30D",
      "updatedAt": 1761649801241,
      "follower_count": 2612,
      "smart_follower_count": 5,
      "insightfullness": null,
      "originality": null,
      "yaps_all": null
    },
    {
      "id": 8191123,
      "name": "Swisssaint",
      "rank": 20,
      "user_id": "-1",
      "topic_id": "IQ",
      "username": "alliwaris_55",
      "mindshare": 1.15,
      "projectId": 56,
      "duration": "30D",
      "updatedAt": 1761649801241,
      "follower_count": 2412,
      "smart_follower_count": 6,
      "insightfullness": null,
      "originality": null,
      "yaps_all": null
    },
    {
      "id": 8191124,
      "name": "Pels💹",
      "rank": 21,
      "user_id": "-1",
      "topic_id": "IQ",
      "username": "pelscrypt",
      "mindshare": 0.88,
      "projectId": 56,
      "duration": "30D",
      "updatedAt": 1761649801241,
      "follower_count": 2595,
      "smart_follower_count": 7,
      "insightfullness": null,
      "originality": null,
      "yaps_all": null
    },
    {
      "id": 8191125,
      "name": "deefx💯🔥",
      "rank": 22,
      "user_id": "-1",
      "topic_id": "IQ",
      "username": "davidfx167",
      "mindshare": 0.88,
      "projectId": 56,
      "duration": "30D",
      "updatedAt": 1761649801241,
      "follower_count": 788,
      "smart_follower_count": 1,
      "insightfullness": null,
      "originality": null,
      "yaps_all": null
    },
    {
      "id": 8191126,
      "name": "Nifemi",
      "rank": 23,
      "user_id": "-1",
      "topic_id": "IQ",
      "username": "wckdNifemi",
      "mindshare": 0.75,
      "projectId": 56,
      "duration": "30D",
      "updatedAt": 1761649801241,
      "follower_count": 1769,
      "smart_follower_count": 5,
      "insightfullness": null,
      "originality": null,
      "yaps_all": null
    },
    {
      "id": 8191127,
      "name": "RICHOBA.SOL",
      "rank": 24,
      "user_id": "-1",
      "topic_id": "IQ",
      "username": "Richobahhh",
      "mindshare": 0.61,
      "projectId": 56,
      "duration": "30D",
      "updatedAt": 1761649801241,
      "follower_count": 3679,
      "smart_follower_count": 14,
      "insightfullness": null,
      "originality": null,
      "yaps_all": null
    },
    {
      "id": 8191128,
      "name": "Pedro",
      "rank": 25,
      "user_id": "-1",
      "topic_id": "IQ",
      "username": "PED_CREATIVE",
      "mindshare": 0.56,
      "projectId": 56,
      "duration": "30D",
      "updatedAt": 1761649801241,
      "follower_count": 2739,
      "smart_follower_count": 20,
      "insightfullness": null,
      "originality": null,
      "yaps_all": null
    },
    {
      "id": 8798600,
      "name": "456girlⓂ️Ⓜ️T",
      "rank": 26,
      "user_id": "-1",
      "topic_id": "IQ",
      "username": "456girls",
      "mindshare": 0.54,
      "projectId": 56,
      "duration": "30D",
      "updatedAt": 1761649801241,
      "follower_count": 2830,
      "smart_follower_count": 28,
      "insightfullness": null,
      "originality": null,
      "yaps_all": null
    },
    {
      "id": 8798601,
      "name": "DanielBest🐐 | 𝔽rAI",
      "rank": 27,
      "user_id": "-1",
      "topic_id": "IQ",
      "username": "DanielBest63181",
      "mindshare": 0.53,
      "projectId": 56,
      "duration": "30D",
      "updatedAt": 1761649801241,
      "follower_count": 1134,
      "smart_follower_count": 1,
      "insightfullness": null,
      "originality": null,
      "yaps_all": null
    },
    {
      "id": 17235464,
      "name": "심문관 IQ2050",
      "rank": 28,
      "user_id": "-1",
      "topic_id": "IQ",
      "username": "4Years1219",
      "mindshare": 0.36,
      "projectId": 56,
      "duration": "30D",
      "updatedAt": 1761649801241,
      "follower_count": 2466,
      "smart_follower_count": 52,
      "insightfullness": null,
      "originality": null,
      "yaps_all": null
    },
    {
      "id": 17737934,
      "name": "Tian (天)",
      "rank": 29,
      "user_id": "-1",
      "topic_id": "IQ",
      "username": "DTIAN99",
      "mindshare": 0.08,
      "projectId": 56,
      "duration": "30D",
      "updatedAt": 1761649801241,
      "follower_count": 1082,
      "smart_follower_count": 3,
      "insightfullness": null,
      "originality": null,
      "yaps_all": null
    },
    {
      "id": 18123500,
      "name": "인토 eco currency 🌊RIVER",
      "rank": 30,
      "user_id": "-1",
      "topic_id": "IQ",
      "username": "KFood13",
      "mindshare": 0.04,
      "projectId": 56,
      "duration": "30D",
      "updatedAt": 1761649801241,
      "follower_count": 5370,
      "smart_follower_count": 64,
      "insightfullness": null,
      "originality": null,
      "yaps_all": null
    },
    {
      "id": 18123501,
      "name": "EnochOFGod",
      "rank": 31,
      "user_id": "-1",
      "topic_id": "IQ",
      "username": "Enoch_Of_God",
      "mindshare": 0.03,
      "projectId": 56,
      "duration": "30D",
      "updatedAt": 1761649801241,
      "follower_count": 2709,
      "smart_follower_count": 2,
      "insightfullness": null,
      "originality": null,
      "yaps_all": null
    },
    {
      "id": 19282259,
      "name": "Ngozi Ugochukwu (Ø,G)",
      "rank": 32,
      "user_id": "-1",
      "topic_id": "IQ",
      "username": "UgochukwuCrypt",
      "mindshare": 0.1,
      "projectId": 56,
      "duration": "30D",
      "updatedAt": 1761033487603,
      "follower_count": 148,
      "smart_follower_count": 2,
      "insightfullness": null,
      "originality": null,
      "yaps_all": null
    },
    {
      "id": 28418113,
      "name": "인토 eco currency",
      "rank": 33,
      "user_id": "-1",
      "topic_id": "IQ",
      "username": "KFood13",
      "mindshare": 0.11,
      "projectId": 56,
      "duration": "30D",
      "updatedAt": 1760957947639,
      "follower_count": 5378,
      "smart_follower_count": 64,
      "insightfullness": null,
      "originality": null,
      "yaps_all": null
    }
  ]
}